[
  { "nodeid": 0, "depth": 0, "split": "f5", "split_condition": 2.84065826e-10, "yes": 1, "no": 2, "missing": 2 , "children": [
    { "nodeid": 1, "depth": 1, "split": "f5", "split_condition": 2.35363506e-10, "yes": 3, "no": 4, "missing": 4 , "children": [
      { "nodeid": 3, "leaf": -0.196694121 }, 
      { "nodeid": 4, "leaf": -0.0638602749 }
    ]}, 
    { "nodeid": 2, "depth": 1, "split": "f6", "split_condition": 0.64340663, "yes": 5, "no": 6, "missing": 6 , "children": [
      { "nodeid": 5, "depth": 2, "split": "f7", "split_condition": 1.40574431, "yes": 7, "no": 8, "missing": 8 , "children": [
        { "nodeid": 7, "leaf": -0.0917477533 }, 
        { "nodeid": 8, "leaf": 0.0343396328 }
      ]}, 
      { "nodeid": 6, "depth": 2, "split": "f0", "split_condition": 0.352295727, "yes": 9, "no": 10, "missing": 10 , "children": [
        { "nodeid": 9, "leaf": -0.0134359552 }, 
        { "nodeid": 10, "leaf": 0.0648079142 }
      ]}
    ]}
  ]},
  { "nodeid": 0, "depth": 0, "split": "f5", "split_condition": 2.84065826e-10, "yes": 1, "no": 2, "missing": 2 , "children": [
    { "nodeid": 1, "depth": 1, "split": "f5", "split_condition": 2.35363506e-10, "yes": 3, "no": 4, "missing": 4 , "children": [
      { "nodeid": 3, "leaf": -0.170879051 }, 
      { "nodeid": 4, "leaf": -0.0604745261 }
    ]}, 
    { "nodeid": 2, "depth": 1, "split": "f6", "split_condition": 0.64340663, "yes": 5, "no": 6, "missing": 6 , "children": [
      { "nodeid": 5, "depth": 2, "split": "f7", "split_condition": 1.40574431, "yes": 7, "no": 8, "missing": 8 , "children": [
        { "nodeid": 7, "leaf": -0.0862945393 }, 
        { "nodeid": 8, "leaf": 0.0337672681 }
      ]}, 
      { "nodeid": 6, "depth": 2, "split": "f6", "split_condition": 2.33480096, "yes": 9, "no": 10, "missing": 10 , "children": [
        { "nodeid": 9, "leaf": 0.0638148561 }, 
        { "nodeid": 10, "leaf": -0.0145821515 }
      ]}
    ]}
  ]},
  { "nodeid": 0, "depth": 0, "split": "f5", "split_condition": 2.84065826e-10, "yes": 1, "no": 2, "missing": 2 , "children": [
    { "nodeid": 1, "depth": 1, "split": "f8", "split_condition": 0.846063256, "yes": 3, "no": 4, "missing": 4 , "children": [
      { "nodeid": 3, "depth": 2, "split": "f8", "split_condition": -1.05530953, "yes": 7, "no": 8, "missing": 8 , "children": [
        { "nodeid": 7, "leaf": -0.0394175388 }, 
        { "nodeid": 8, "leaf": -0.153428003 }
      ]}, 
      { "nodeid": 4, "leaf": -0.0377836637 }
    ]}, 
    { "nodeid": 2, "depth": 1, "split": "f6", "split_condition": 0.64340663, "yes": 5, "no": 6, "missing": 6 , "children": [
      { "nodeid": 5, "depth": 2, "split": "f7", "split_condition": 1.40574431, "yes": 9, "no": 10, "missing": 10 , "children": [
        { "nodeid": 9, "leaf": -0.0813825428 }, 
        { "nodeid": 10, "leaf": 0.0332112871 }
      ]}, 
      { "nodeid": 6, "depth": 2, "split": "f0", "split_condition": 0.352295727, "yes": 11, "no": 12, "missing": 12 , "children": [
        { "nodeid": 11, "leaf": -0.0141497049 }, 
        { "nodeid": 12, "leaf": 0.0628811345 }
      ]}
    ]}
  ]},
  { "nodeid": 0, "depth": 0, "split": "f5", "split_condition": 2.84065826e-10, "yes": 1, "no": 2, "missing": 2 , "children": [
    { "nodeid": 1, "depth": 1, "split": "f5", "split_condition": 2.35363506e-10, "yes": 3, "no": 4, "missing": 4 , "children": [
      { "nodeid": 3, "leaf": -0.13807711 }, 
      { "nodeid": 4, "leaf": -0.0525514968 }
    ]}, 
    { "nodeid": 2, "depth": 1, "split": "f3", "split_condition": 0.371746629, "yes": 5, "no": 6, "missing": 6 , "children": [
      { "nodeid": 5, "depth": 2, "split": "f0", "split_condition": 0.306376815, "yes": 7, "no": 8, "missing": 8 , "children": [
        { "nodeid": 7, "leaf": -0.0363099687 }, 
        { "nodeid": 8, "leaf": 0.06207335 }
      ]}, 
      { "nodeid": 6, "leaf": -0.0893837586 }
    ]}
  ]},
  { "nodeid": 0, "depth": 0, "split": "f5", "split_condition": 2.84065826e-10, "yes": 1, "no": 2, "missing": 2 , "children": [
    { "nodeid": 1, "depth": 1, "split": "f8", "split_condition": 0.846063256, "yes": 3, "no": 4, "missing": 4 , "children": [
      { "nodeid": 3, "depth": 2, "split": "f8", "split_condition": -1.05530953, "yes": 7, "no": 8, "missing": 8 , "children": [
        { "nodeid": 7, "leaf": -0.0352052487 }, 
        { "nodeid": 8, "leaf": -0.127640471 }
      ]}, 
      { "nodeid": 4, "leaf": -0.0331216864 }
    ]}, 
    { "nodeid": 2, "depth": 1, "split": "f3", "split_condition": 0.371746629, "yes": 5, "no": 6, "missing": 6 , "children": [
      { "nodeid": 5, "depth": 2, "split": "f0", "split_condition": 0.306376815, "yes": 9, "no": 10, "missing": 10 , "children": [
        { "nodeid": 9, "leaf": -0.0348418355 }, 
        { "nodeid": 10, "leaf": 0.0612637587 }
      ]}, 
      { "nodeid": 6, "leaf": -0.0854626447 }
    ]}
  ]},
  { "nodeid": 0, "depth": 0, "split": "f5", "split_condition": 2.84065826e-10, "yes": 1, "no": 2, "missing": 2 , "children": [
    { "nodeid": 1, "depth": 1, "split": "f5", "split_condition": 2.35363506e-10, "yes": 3, "no": 4, "missing": 4 , "children": [
      { "nodeid": 3, "leaf": -0.117721535 }, 
      { "nodeid": 4, "depth": 2, "split": "f3", "split_condition": 0.146231398, "yes": 7, "no": 8, "missing": 8 , "children": [
        { "nodeid": 7, "leaf": 0.0108675435 }, 
        { "nodeid": 8, "leaf": -0.079101257 }
      ]}
    ]}, 
    { "nodeid": 2, "depth": 1, "split": "f3", "split_condition": 0.371746629, "yes": 5, "no": 6, "missing": 6 , "children": [
      { "nodeid": 5, "depth": 2, "split": "f0", "split_condition": 0.306376815, "yes": 9, "no": 10, "missing": 10 , "children": [
        { "nodeid": 9, "leaf": -0.0334485695 }, 
        { "nodeid": 10, "leaf": 0.0605087392 }
      ]}, 
      { "nodeid": 6, "leaf": -0.0818531662 }
    ]}
  ]},
  { "nodeid": 0, "depth": 0, "split": "f5", "split_condition": 2.84065826e-10, "yes": 1, "no": 2, "missing": 2 , "children": [
    { "nodeid": 1, "depth": 1, "split": "f8", "split_condition": 0.846063256, "yes": 3, "no": 4, "missing": 4 , "children": [
      { "nodeid": 3, "depth": 2, "split": "f8", "split_condition": -1.05530953, "yes": 7, "no": 8, "missing": 8 , "children": [
        { "nodeid": 7, "leaf": -0.0327226147 }, 
        { "nodeid": 8, "leaf": -0.110685818 }
      ]}, 
      { "nodeid": 4, "leaf": -0.029931888 }
    ]}, 
    { "nodeid": 2, "depth": 1, "split": "f3", "split_condition": 0.371746629, "yes": 5, "no": 6, "missing": 6 , "children": [
      { "nodeid": 5, "depth": 2, "split": "f0", "split_condition": 0.306376815, "yes": 9, "no": 10, "missing": 10 , "children": [
        { "nodeid": 9, "leaf": -0.0321250707 }, 
        { "nodeid": 10, "leaf": 0.0598031655 }
      ]}, 
      { "nodeid": 6, "leaf": -0.0785260871 }
    ]}
  ]},
  { "nodeid": 0, "depth": 0, "split": "f5", "split_condition": 2.84065826e-10, "yes": 1, "no": 2, "missing": 2 , "children": [
    { "nodeid": 1, "depth": 1, "split": "f5", "split_condition": 2.35363506e-10, "yes": 3, "no": 4, "missing": 4 , "children": [
      { "nodeid": 3, "leaf": -0.103880003 }, 
      { "nodeid": 4, "depth": 2, "split": "f3", "split_condition": 0.146231398, "yes": 7, "no": 8, "missing": 8 , "children": [
        { "nodeid": 7, "leaf": 0.0113446414 }, 
        { "nodeid": 8, "leaf": -0.0718091279 }
      ]}
    ]}, 
    { "nodeid": 2, "depth": 1, "split": "f3", "split_condition": 0.371746629, "yes": 5, "no": 6, "missing": 6 , "children": [
      { "nodeid": 5, "depth": 2, "split": "f0", "split_condition": 0.306376815, "yes": 9, "no": 10, "missing": 10 , "children": [
        { "nodeid": 9, "leaf": -0.0308666565 }, 
        { "nodeid": 10, "leaf": 0.0591425002 }
      ]}, 
      { "nodeid": 6, "leaf": -0.0754544064 }
    ]}
  ]},
  { "nodeid": 0, "depth": 0, "split": "f5", "split_condition": 2.84065826e-10, "yes": 1, "no": 2, "missing": 2 , "children": [
    { "nodeid": 1, "depth": 1, "split": "f5", "split_condition": 2.35363506e-10, "yes": 3, "no": 4, "missing": 4 , "children": [
      { "nodeid": 3, "leaf": -0.0983874425 }, 
      { "nodeid": 4, "depth": 2, "split": "f3", "split_condition": 0.146231398, "yes": 7, "no": 8, "missing": 8 , "children": [
        { "nodeid": 7, "leaf": 0.0110835591 }, 
        { "nodeid": 8, "leaf": -0.0692284331 }
      ]}
    ]}, 
    { "nodeid": 2, "depth": 1, "split": "f3", "split_condition": 0.371746629, "yes": 5, "no": 6, "missing": 6 , "children": [
      { "nodeid": 5, "depth": 2, "split": "f0", "split_condition": 0.306376815, "yes": 9, "no": 10, "missing": 10 , "children": [
        { "nodeid": 9, "leaf": -0.0296690557 }, 
        { "nodeid": 10, "leaf": 0.0585226715 }
      ]}, 
      { "nodeid": 6, "leaf": -0.0726134926 }
    ]}
  ]},
  { "nodeid": 0, "depth": 0, "split": "f5", "split_condition": 2.84065826e-10, "yes": 1, "no": 2, "missing": 2 , "children": [
    { "nodeid": 1, "depth": 1, "split": "f8", "split_condition": 0.846063256, "yes": 3, "no": 4, "missing": 4 , "children": [
      { "nodeid": 3, "leaf": -0.0924151987 }, 
      { "nodeid": 4, "leaf": -0.0255133249 }
    ]}, 
    { "nodeid": 2, "depth": 1, "split": "f3", "split_condition": 0.371746629, "yes": 5, "no": 6, "missing": 6 , "children": [
      { "nodeid": 5, "depth": 2, "split": "f0", "split_condition": 0.306376815, "yes": 7, "no": 8, "missing": 8 , "children": [
        { "nodeid": 7, "leaf": -0.0285283159 }, 
        { "nodeid": 8, "leaf": 0.0579400659 }
      ]}, 
      { "nodeid": 6, "leaf": -0.0699810237 }
    ]}
  ]},
  { "nodeid": 0, "depth": 0, "split": "f5", "split_condition": 2.84065826e-10, "yes": 1, "no": 2, "missing": 2 , "children": [
    { "nodeid": 1, "depth": 1, "split": "f5", "split_condition": 2.35363506e-10, "yes": 3, "no": 4, "missing": 4 , "children": [
      { "nodeid": 3, "leaf": -0.089738436 }, 
      { "nodeid": 4, "depth": 2, "split": "f3", "split_condition": 0.146231398, "yes": 7, "no": 8, "missing": 8 , "children": [
        { "nodeid": 7, "leaf": 0.0123497276 }, 
        { "nodeid": 8, "leaf": -0.063767612 }
      ]}
    ]}, 
    { "nodeid": 2, "depth": 1, "split": "f3", "split_condition": 0.371746629, "yes": 5, "no": 6, "missing": 6 , "children": [
      { "nodeid": 5, "depth": 2, "split": "f0", "split_condition": 0.306376815, "yes": 9, "no": 10, "missing": 10 , "children": [
        { "nodeid": 9, "leaf": -0.0274408348 }, 
        { "nodeid": 10, "leaf": 0.0573914312 }
      ]}, 
      { "nodeid": 6, "leaf": -0.0675368831 }
    ]}
  ]},
  { "nodeid": 0, "depth": 0, "split": "f5", "split_condition": 2.84065826e-10, "yes": 1, "no": 2, "missing": 2 , "children": [
    { "nodeid": 1, "depth": 1, "split": "f5", "split_condition": 2.35363506e-10, "yes": 3, "no": 4, "missing": 4 , "children": [
      { "nodeid": 3, "leaf": -0.0861254558 }, 
      { "nodeid": 4, "depth": 2, "split": "f3", "split_condition": 0.146231398, "yes": 7, "no": 8, "missing": 8 , "children": [
        { "nodeid": 7, "leaf": 0.01206432 }, 
        { "nodeid": 8, "leaf": -0.061741937 }
      ]}
    ]}, 
    { "nodeid": 2, "depth": 1, "split": "f3", "split_condition": 0.371746629, "yes": 5, "no": 6, "missing": 6 , "children": [
      { "nodeid": 5, "depth": 2, "split": "f0", "split_condition": 0.306376815, "yes": 9, "no": 10, "missing": 10 , "children": [
        { "nodeid": 9, "leaf": -0.0264032967 }, 
        { "nodeid": 10, "leaf": 0.0568737946 }
      ]}, 
      { "nodeid": 6, "leaf": -0.0652629882 }
    ]}
  ]},
  { "nodeid": 0, "depth": 0, "split": "f5", "split_condition": 2.84065826e-10, "yes": 1, "no": 2, "missing": 2 , "children": [
    { "nodeid": 1, "depth": 1, "split": "f8", "split_condition": 0.846063256, "yes": 3, "no": 4, "missing": 4 , "children": [
      { "nodeid": 3, "depth": 2, "split": "f8", "split_condition": -1.05530953, "yes": 7, "no": 8, "missing": 8 , "children": [
        { "nodeid": 7, "leaf": -0.0250800401 }, 
        { "nodeid": 8, "leaf": -0.0833681077 }
      ]}, 
      { "nodeid": 4, "leaf": -0.0219073966 }
    ]}, 
    { "nodeid": 2, "depth": 1, "split": "f3", "split_condition": 0.371746629, "yes": 5, "no": 6, "missing": 6 , "children": [
      { "nodeid": 5, "depth": 2, "split": "f0", "split_condition": 0.306376815, "yes": 9, "no": 10, "missing": 10 , "children": [
        { "nodeid": 9, "leaf": -0.0254126675 }, 
        { "nodeid": 10, "leaf": 0.0563845038 }
      ]}, 
      { "nodeid": 6, "leaf": -0.0631431714 }
    ]}
  ]},
  { "nodeid": 0, "depth": 0, "split": "f5", "split_condition": 2.84065826e-10, "yes": 1, "no": 2, "missing": 2 , "children": [
    { "nodeid": 1, "depth": 1, "split": "f5", "split_condition": 2.35363506e-10, "yes": 3, "no": 4, "missing": 4 , "children": [
      { "nodeid": 3, "leaf": -0.080243133 }, 
      { "nodeid": 4, "depth": 2, "split": "f3", "split_condition": 0.146231398, "yes": 7, "no": 8, "missing": 8 , "children": [
        { "nodeid": 7, "leaf": 0.0123364571 }, 
        { "nodeid": 8, "leaf": -0.057390023 }
      ]}
    ]}, 
    { "nodeid": 2, "depth": 1, "split": "f3", "split_condition": 0.371746629, "yes": 5, "no": 6, "missing": 6 , "children": [
      { "nodeid": 5, "depth": 2, "split": "f0", "split_condition": 0.306376815, "yes": 9, "no": 10, "missing": 10 , "children": [
        { "nodeid": 9, "leaf": -0.0244661365 }, 
        { "nodeid": 10, "leaf": 0.0559211634 }
      ]}, 
      { "nodeid": 6, "leaf": -0.0611629374 }
    ]}
  ]},
  { "nodeid": 0, "depth": 0, "split": "f5", "split_condition": 2.84065826e-10, "yes": 1, "no": 2, "missing": 2 , "children": [
    { "nodeid": 1, "depth": 1, "split": "f5", "split_condition": 2.35363506e-10, "yes": 3, "no": 4, "missing": 4 , "children": [
      { "nodeid": 3, "leaf": -0.0776934326 }, 
      { "nodeid": 4, "depth": 2, "split": "f3", "split_condition": 0.146231398, "yes": 7, "no": 8, "missing": 8 , "children": [
        { "nodeid": 7, "leaf": 0.0120513747 }, 
        { "nodeid": 8, "leaf": -0.0557634123 }
      ]}
    ]}, 
    { "nodeid": 2, "depth": 1, "split": "f3", "split_condition": 0.371746629, "yes": 5, "no": 6, "missing": 6 , "children": [
      { "nodeid": 5, "depth": 2, "split": "f0", "split_condition": 0.306376815, "yes": 9, "no": 10, "missing": 10 , "children": [
        { "nodeid": 9, "leaf": -0.0235611107 }, 
        { "nodeid": 10, "leaf": 0.0554815494 }
      ]}, 
      { "nodeid": 6, "leaf": -0.0593093447 }
    ]}
  ]},
  { "nodeid": 0, "depth": 0, "split": "f5", "split_condition": 2.84065826e-10, "yes": 1, "no": 2, "missing": 2 , "children": [
    { "nodeid": 1, "depth": 1, "split": "f8", "split_condition": 0.846063256, "yes": 3, "no": 4, "missing": 4 , "children": [
      { "nodeid": 3, "depth": 2, "split": "f8", "split_condition": -1.05530953, "yes": 7, "no": 8, "missing": 8 , "children": [
        { "nodeid": 7, "leaf": -0.023001438 }, 
        { "nodeid": 8, "leaf": -0.0757493824 }
      ]}, 
      { "nodeid": 4, "leaf": -0.0188533012 }
    ]}, 
    { "nodeid": 2, "depth": 1, "split": "f3", "split_condition": 0.371746629, "yes": 5, "no": 6, "missing": 6 , "children": [
      { "nodeid": 5, "depth": 2, "split": "f0", "split_condition": 0.306376815, "yes": 9, "no": 10, "missing": 10 , "children": [
        { "nodeid": 9, "leaf": -0.0226952266 }, 
        { "nodeid": 10, "leaf": 0.0550636761 }
      ]}, 
      { "nodeid": 6, "leaf": -0.0575708114 }
    ]}
  ]},
  { "nodeid": 0, "depth": 0, "split": "f5", "split_condition": 2.84065826e-10, "yes": 1, "no": 2, "missing": 2 , "children": [
    { "nodeid": 1, "depth": 1, "split": "f5", "split_condition": 2.35363506e-10, "yes": 3, "no": 4, "missing": 4 , "children": [
      { "nodeid": 3, "leaf": -0.0734484121 }, 
      { "nodeid": 4, "depth": 2, "split": "f3", "split_condition": 0.146231398, "yes": 7, "no": 8, "missing": 8 , "children": [
        { "nodeid": 7, "leaf": 0.0122669712 }, 
        { "nodeid": 8, "leaf": -0.0522255898 }
      ]}
    ]}, 
    { "nodeid": 2, "depth": 1, "split": "f3", "split_condition": 0.371746629, "yes": 5, "no": 6, "missing": 6 , "children": [
      { "nodeid": 5, "depth": 2, "split": "f0", "split_condition": 0.306376815, "yes": 9, "no": 10, "missing": 10 , "children": [
        { "nodeid": 9, "leaf": -0.0218662526 }, 
        { "nodeid": 10, "leaf": 0.0546656922 }
      ]}, 
      { "nodeid": 6, "leaf": -0.0559369698 }
    ]}
  ]},
  { "nodeid": 0, "depth": 0, "split": "f5", "split_condition": 2.84065826e-10, "yes": 1, "no": 2, "missing": 2 , "children": [
    { "nodeid": 1, "depth": 1, "split": "f5", "split_condition": 2.35363506e-10, "yes": 3, "no": 4, "missing": 4 , "children": [
      { "nodeid": 3, "leaf": -0.0715553984 }, 
      { "nodeid": 4, "depth": 2, "split": "f3", "split_condition": 0.146231398, "yes": 7, "no": 8, "missing": 8 , "children": [
        { "nodeid": 7, "leaf": 0.0119835911 }, 
        { "nodeid": 8, "leaf": -0.0508902557 }
      ]}
    ]}, 
    { "nodeid": 2, "depth": 1, "split": "f3", "split_condition": 0.371746629, "yes": 5, "no": 6, "missing": 6 , "children": [
      { "nodeid": 5, "depth": 2, "split": "f4", "split_condition": 0.573569179, "yes": 9, "no": 10, "missing": 10 , "children": [
        { "nodeid": 9, "leaf": -0.0196289904 }, 
        { "nodeid": 10, "leaf": 0.0544560663 }
      ]}, 
      { "nodeid": 6, "leaf": -0.0543985851 }
    ]}
  ]},
  { "nodeid": 0, "depth": 0, "split": "f5", "split_condition": 2.84065826e-10, "yes": 1, "no": 2, "missing": 2 , "children": [
    { "nodeid": 1, "depth": 1, "split": "f8", "split_condition": 0.846063256, "yes": 3, "no": 4, "missing": 4 , "children": [
      { "nodeid": 3, "depth": 2, "split": "f8", "split_condition": -1.05530953, "yes": 7, "no": 8, "missing": 8 , "children": [
        { "nodeid": 7, "leaf": -0.0212236103 }, 
        { "nodeid": 8, "leaf": -0.0701177493 }
      ]}, 
      { "nodeid": 4, "leaf": -0.0162063502 }
    ]}, 
    { "nodeid": 2, "depth": 1, "split": "f4", "split_condition": 0.590335727, "yes": 5, "no": 6, "missing": 6 , "children": [
      { "nodeid": 5, "depth": 2, "split": "f3", "split_condition": 0.206497744, "yes": 9, "no": 10, "missing": 10 , "children": [
        { "nodeid": 9, "leaf": 0.0101669263 }, 
        { "nodeid": 10, "leaf": -0.0619470663 }
      ]}, 
      { "nodeid": 6, "depth": 2, "split": "f2", "split_condition": 0.336584032, "yes": 11, "no": 12, "missing": 12 , "children": [
        { "nodeid": 11, "leaf": 0.0540434681 }, 
        { "nodeid": 12, "leaf": -0.00829491206 }
      ]}
    ]}
  ]},
  { "nodeid": 0, "depth": 0, "split": "f5", "split_condition": 2.84065826e-10, "yes": 1, "no": 2, "missing": 2 , "children": [
    { "nodeid": 1, "depth": 1, "split": "f5", "split_condition": 2.35363506e-10, "yes": 3, "no": 4, "missing": 4 , "children": [
      { "nodeid": 3, "leaf": -0.068354778 }, 
      { "nodeid": 4, "depth": 2, "split": "f3", "split_condition": 0.146231398, "yes": 7, "no": 8, "missing": 8 , "children": [
        { "nodeid": 7, "leaf": 0.0121518327 }, 
        { "nodeid": 8, "leaf": -0.0479379334 }
      ]}
    ]}, 
    { "nodeid": 2, "depth": 1, "split": "f4", "split_condition": 0.590335727, "yes": 5, "no": 6, "missing": 6 , "children": [
      { "nodeid": 5, "depth": 2, "split": "f3", "split_condition": 0.206497744, "yes": 9, "no": 10, "missing": 10 , "children": [
        { "nodeid": 9, "leaf": 0.00986890402 }, 
        { "nodeid": 10, "leaf": -0.0601034164 }
      ]}, 
      { "nodeid": 6, "depth": 2, "split": "f3", "split_condition": 0.34342438, "yes": 11, "no": 12, "missing": 12 , "children": [
        { "nodeid": 11, "leaf": 0.0536898449 }, 
        { "nodeid": 12, "leaf": -0.00837480277 }
      ]}
    ]}
  ]},
  { "nodeid": 0, "depth": 0, "split": "f5", "split_condition": 2.84065826e-10, "yes": 1, "no": 2, "missing": 2 , "children": [
    { "nodeid": 1, "depth": 1, "split": "f5", "split_condition": 2.35363506e-10, "yes": 3, "no": 4, "missing": 4 , "children": [
      { "nodeid": 3, "leaf": -0.0668931305 }, 
      { "nodeid": 4, "depth": 2, "split": "f3", "split_condition": 0.146231398, "yes": 7, "no": 8, "missing": 8 , "children": [
        { "nodeid": 7, "leaf": 0.011871255 }, 
        { "nodeid": 8, "leaf": -0.0468201414 }
      ]}
    ]}, 
    { "nodeid": 2, "depth": 1, "split": "f4", "split_condition": 0.590335727, "yes": 5, "no": 6, "missing": 6 , "children": [
      { "nodeid": 5, "depth": 2, "split": "f3", "split_condition": 0.206497744, "yes": 9, "no": 10, "missing": 10 , "children": [
        { "nodeid": 9, "leaf": 0.0095793223 }, 
        { "nodeid": 10, "leaf": -0.0583705567 }
      ]}, 
      { "nodeid": 6, "depth": 2, "split": "f3", "split_condition": 0.34342438, "yes": 11, "no": 12, "missing": 12 , "children": [
        { "nodeid": 11, "leaf": 0.0533479564 }, 
        { "nodeid": 12, "leaf": -0.00814938825 }
      ]}
    ]}
  ]},
  { "nodeid": 0, "depth": 0, "split": "f5", "split_condition": 2.84065826e-10, "yes": 1, "no": 2, "missing": 2 , "children": [
    { "nodeid": 1, "depth": 1, "split": "f8", "split_condition": 0.846063256, "yes": 3, "no": 4, "missing": 4 , "children": [
      { "nodeid": 3, "depth": 2, "split": "f8", "split_condition": -1.05530953, "yes": 7, "no": 8, "missing": 8 , "children": [
        { "nodeid": 7, "leaf": -0.0196832251 }, 
        { "nodeid": 8, "leaf": -0.0657888874 }
      ]}, 
      { "nodeid": 4, "leaf": -0.0138727846 }
    ]}, 
    { "nodeid": 2, "depth": 1, "split": "f4", "split_condition": 0.590335727, "yes": 5, "no": 6, "missing": 6 , "children": [
      { "nodeid": 5, "depth": 2, "split": "f5", "split_condition": 6.24752194e-10, "yes": 9, "no": 10, "missing": 10 , "children": [
        { "nodeid": 9, "leaf": -0.0493854694 }, 
        { "nodeid": 10, "leaf": 0.0175096896 }
      ]}, 
      { "nodeid": 6, "depth": 2, "split": "f2", "split_condition": 0.336584032, "yes": 11, "no": 12, "missing": 12 , "children": [
        { "nodeid": 11, "leaf": 0.0530212112 }, 
        { "nodeid": 12, "leaf": -0.00821766537 }
      ]}
    ]}
  ]},
  { "nodeid": 0, "depth": 0, "split": "f5", "split_condition": 2.84065826e-10, "yes": 1, "no": 2, "missing": 2 , "children": [
    { "nodeid": 1, "depth": 1, "split": "f5", "split_condition": 2.35363506e-10, "yes": 3, "no": 4, "missing": 4 , "children": [
      { "nodeid": 3, "leaf": -0.0643943995 }, 
      { "nodeid": 4, "depth": 2, "split": "f3", "split_condition": 0.146231398, "yes": 7, "no": 8, "missing": 8 , "children": [
        { "nodeid": 7, "leaf": 0.0119993975 }, 
        { "nodeid": 8, "leaf": -0.0443016887 }
      ]}
    ]}, 
    { "nodeid": 2, "depth": 1, "split": "f3", "split_condition": 0.371746629, "yes": 5, "no": 6, "missing": 6 , "children": [
      { "nodeid": 5, "depth": 2, "split": "f0", "split_condition": 0.306376815, "yes": 9, "no": 10, "missing": 10 , "children": [
        { "nodeid": 9, "leaf": -0.0212258846 }, 
        { "nodeid": 10, "leaf": 0.0526825152 }
      ]}, 
      { "nodeid": 6, "leaf": -0.0491570421 }
    ]}
  ]},
  { "nodeid": 0, "depth": 0, "split": "f5", "split_condition": 2.84065826e-10, "yes": 1, "no": 2, "missing": 2 , "children": [
    { "nodeid": 1, "depth": 1, "split": "f5", "split_condition": 2.35363506e-10, "yes": 3, "no": 4, "missing": 4 , "children": [
      { "nodeid": 3, "leaf": -0.0632288456 }, 
      { "nodeid": 4, "depth": 2, "split": "f3", "split_condition": 0.146231398, "yes": 7, "no": 8, "missing": 8 , "children": [
        { "nodeid": 7, "leaf": 0.0117225237 }, 
        { "nodeid": 8, "leaf": -0.0433498733 }
      ]}
    ]}, 
    { "nodeid": 2, "depth": 1, "split": "f4", "split_condition": 0.590335727, "yes": 5, "no": 6, "missing": 6 , "children": [
      { "nodeid": 5, "depth": 2, "split": "f5", "split_condition": 6.24752194e-10, "yes": 9, "no": 10, "missing": 10 , "children": [
        { "nodeid": 9, "leaf": -0.0472322218 }, 
        { "nodeid": 10, "leaf": 0.0169574898 }
      ]}, 
      { "nodeid": 6, "depth": 2, "split": "f3", "split_condition": 0.34342438, "yes": 11, "no": 12, "missing": 12 , "children": [
        { "nodeid": 11, "leaf": 0.0524193719 }, 
        { "nodeid": 12, "leaf": -0.00817090645 }
      ]}
    ]}
  ]},
  { "nodeid": 0, "depth": 0, "split": "f5", "split_condition": 2.84065826e-10, "yes": 1, "no": 2, "missing": 2 , "children": [
    { "nodeid": 1, "depth": 1, "split": "f8", "split_condition": 0.846063256, "yes": 3, "no": 4, "missing": 4 , "children": [
      { "nodeid": 3, "depth": 2, "split": "f8", "split_condition": -1.05530953, "yes": 7, "no": 8, "missing": 8 , "children": [
        { "nodeid": 7, "leaf": -0.0183357801 }, 
        { "nodeid": 8, "leaf": -0.062353231 }
      ]}, 
      { "nodeid": 4, "leaf": -0.0117891412 }
    ]}, 
    { "nodeid": 2, "depth": 1, "split": "f4", "split_condition": 0.590335727, "yes": 5, "no": 6, "missing": 6 , "children": [
      { "nodeid": 5, "depth": 2, "split": "f3", "split_condition": 0.206497744, "yes": 9, "no": 10, "missing": 10 , "children": [
        { "nodeid": 9, "leaf": 0.00969027076 }, 
        { "nodeid": 10, "leaf": -0.0540532954 }
      ]}, 
      { "nodeid": 6, "depth": 2, "split": "f3", "split_condition": 0.34342438, "yes": 11, "no": 12, "missing": 12 , "children": [
        { "nodeid": 11, "leaf": 0.0521214418 }, 
        { "nodeid": 12, "leaf": -0.00795448292 }
      ]}
    ]}
  ]},
  { "nodeid": 0, "depth": 0, "split": "f5", "split_condition": 2.56728999e-10, "yes": 1, "no": 2, "missing": 2 , "children": [
    { "nodeid": 1, "depth": 1, "split": "f8", "split_condition": -1.05530953, "yes": 3, "no": 4, "missing": 4 , "children": [
      { "nodeid": 3, "leaf": -0.0178449303 }, 
      { "nodeid": 4, "leaf": -0.0615234487 }
    ]}, 
    { "nodeid": 2, "depth": 1, "split": "f3", "split_condition": 0.371746629, "yes": 5, "no": 6, "missing": 6 , "children": [
      { "nodeid": 5, "depth": 2, "split": "f0", "split_condition": 0.311315954, "yes": 7, "no": 8, "missing": 8 , "children": [
        { "nodeid": 7, "depth": 3, "split": "f0", "split_condition": 0.239595577, "yes": 9, "no": 10, "missing": 10 , "children": [
          { "nodeid": 9, "leaf": 0.0175863206 }, 
          { "nodeid": 10, "leaf": -0.0363394134 }
        ]}, 
        { "nodeid": 8, "leaf": 0.0518488772 }
      ]}, 
      { "nodeid": 6, "leaf": -0.0493646376 }
    ]}
  ]},
  { "nodeid": 0, "depth": 0, "split": "f5", "split_condition": 2.56728999e-10, "yes": 1, "no": 2, "missing": 2 , "children": [
    { "nodeid": 1, "depth": 1, "split": "f8", "split_condition": -1.05530953, "yes": 3, "no": 4, "missing": 4 , "children": [
      { "nodeid": 3, "leaf": -0.0173681378 }, 
      { "nodeid": 4, "leaf": -0.0605537184 }
    ]}, 
    { "nodeid": 2, "depth": 1, "split": "f3", "split_condition": 0.371746629, "yes": 5, "no": 6, "missing": 6 , "children": [
      { "nodeid": 5, "depth": 2, "split": "f0", "split_condition": 0.311315954, "yes": 7, "no": 8, "missing": 8 , "children": [
        { "nodeid": 7, "depth": 3, "split": "f0", "split_condition": 0.239595577, "yes": 9, "no": 10, "missing": 10 , "children": [
          { "nodeid": 9, "leaf": 0.0171703398 }, 
          { "nodeid": 10, "leaf": -0.0351671539 }
        ]}, 
        { "nodeid": 8, "leaf": 0.0515717342 }
      ]}, 
      { "nodeid": 6, "leaf": -0.0482095815 }
    ]}
  ]},
  { "nodeid": 0, "depth": 0, "split": "f5", "split_condition": 2.56728999e-10, "yes": 1, "no": 2, "missing": 2 , "children": [
    { "nodeid": 1, "depth": 1, "split": "f8", "split_condition": -1.05530953, "yes": 3, "no": 4, "missing": 4 , "children": [
      { "nodeid": 3, "leaf": -0.0169049483 }, 
      { "nodeid": 4, "leaf": -0.0596427098 }
    ]}, 
    { "nodeid": 2, "depth": 1, "split": "f3", "split_condition": 0.371746629, "yes": 5, "no": 6, "missing": 6 , "children": [
      { "nodeid": 5, "depth": 2, "split": "f4", "split_condition": 0.573569179, "yes": 7, "no": 8, "missing": 8 , "children": [
        { "nodeid": 7, "depth": 3, "split": "f0", "split_condition": 0.239595577, "yes": 9, "no": 10, "missing": 10 , "children": [
          { "nodeid": 9, "leaf": 0.0167652648 }, 
          { "nodeid": 10, "leaf": -0.0320056118 }
        ]}, 
        { "nodeid": 8, "leaf": 0.0514591001 }
      ]}, 
      { "nodeid": 6, "leaf": -0.0471106395 }
    ]}
  ]},
  { "nodeid": 0, "depth": 0, "split": "f5", "split_condition": 2.56728999e-10, "yes": 1, "no": 2, "missing": 2 , "children": [
    { "nodeid": 1, "depth": 1, "split": "f8", "split_condition": -1.05530953, "yes": 3, "no": 4, "missing": 4 , "children": [
      { "nodeid": 3, "leaf": -0.0164548922 }, 
      { "nodeid": 4, "leaf": -0.0587845109 }
    ]}, 
    { "nodeid": 2, "depth": 1, "split": "f3", "split_condition": 0.371746629, "yes": 5, "no": 6, "missing": 6 , "children": [
      { "nodeid": 5, "depth": 2, "split": "f0", "split_condition": 0.311315954, "yes": 7, "no": 8, "missing": 8 , "children": [
        { "nodeid": 7, "depth": 3, "split": "f8", "split_condition": 0.438520759, "yes": 9, "no": 10, "missing": 10 , "children": [
          { "nodeid": 9, "leaf": -0.0339853242 }, 
          { "nodeid": 10, "leaf": 0.0164389145 }
        ]}, 
        { "nodeid": 8, "leaf": 0.0510499664 }
      ]}, 
      { "nodeid": 6, "leaf": -0.0460633002 }
    ]}
  ]},
  { "nodeid": 0, "depth": 0, "split": "f5", "split_condition": 2.56728999e-10, "yes": 1, "no": 2, "missing": 2 , "children": [
    { "nodeid": 1, "depth": 1, "split": "f8", "split_condition": -1.05530953, "yes": 3, "no": 4, "missing": 4 , "children": [
      { "nodeid": 3, "leaf": -0.0160175543 }, 
      { "nodeid": 4, "leaf": -0.0579738729 }
    ]}, 
    { "nodeid": 2, "depth": 1, "split": "f3", "split_condition": 0.371746629, "yes": 5, "no": 6, "missing": 6 , "children": [
      { "nodeid": 5, "depth": 2, "split": "f4", "split_condition": 0.573569179, "yes": 7, "no": 8, "missing": 8 , "children": [
        { "nodeid": 7, "depth": 3, "split": "f0", "split_condition": 0.239595577, "yes": 9, "no": 10, "missing": 10 , "children": [
          { "nodeid": 9, "leaf": 0.0162645746 }, 
          { "nodeid": 10, "leaf": -0.0312380735 }
        ]}, 
        { "nodeid": 8, "leaf": 0.0509568043 }
      ]}, 
      { "nodeid": 6, "leaf": -0.0450635366 }
    ]}
  ]},
  { "nodeid": 0, "depth": 0, "split": "f5", "split_condition": 2.56728999e-10, "yes": 1, "no": 2, "missing": 2 , "children": [
    { "nodeid": 1, "depth": 1, "split": "f8", "split_condition": -1.05530953, "yes": 3, "no": 4, "missing": 4 , "children": [
      { "nodeid": 3, "leaf": -0.0155925183 }, 
      { "nodeid": 4, "leaf": -0.0572061539 }
    ]}, 
    { "nodeid": 2, "depth": 1, "split": "f3", "split_condition": 0.371746629, "yes": 5, "no": 6, "missing": 6 , "children": [
      { "nodeid": 5, "depth": 2, "split": "f0", "split_condition": 0.311315954, "yes": 7, "no": 8, "missing": 8 , "children": [
        { "nodeid": 7, "depth": 3, "split": "f8", "split_condition": 0.438520759, "yes": 9, "no": 10, "missing": 10 , "children": [
          { "nodeid": 9, "leaf": -0.0330753438 }, 
          { "nodeid": 10, "leaf": 0.0159358811 }
        ]}, 
        { "nodeid": 8, "leaf": 0.0505511053 }
      ]}, 
      { "nodeid": 6, "leaf": -0.0441077016 }
    ]}
  ]},
  { "nodeid": 0, "depth": 0, "split": "f5", "split_condition": 2.56728999e-10, "yes": 1, "no": 2, "missing": 2 , "children": [
    { "nodeid": 1, "depth": 1, "split": "f8", "split_condition": -1.05530953, "yes": 3, "no": 4, "missing": 4 , "children": [
      { "nodeid": 3, "leaf": -0.0151793761 }, 
      { "nodeid": 4, "leaf": -0.0564771704 }
    ]}, 
    { "nodeid": 2, "depth": 1, "split": "f3", "split_condition": 0.371746629, "yes": 5, "no": 6, "missing": 6 , "children": [
      { "nodeid": 5, "depth": 2, "split": "f4", "split_condition": 0.573569179, "yes": 7, "no": 8, "missing": 8 , "children": [
        { "nodeid": 7, "depth": 3, "split": "f0", "split_condition": 0.239595577, "yes": 9, "no": 10, "missing": 10 , "children": [
          { "nodeid": 9, "leaf": 0.0157855395 }, 
          { "nodeid": 10, "leaf": -0.0305096153 }
        ]}, 
        { "nodeid": 8, "leaf": 0.0504749976 }
      ]}, 
      { "nodeid": 6, "leaf": -0.043192517 }
    ]}
  ]},
  { "nodeid": 0, "depth": 0, "split": "f5", "split_condition": 2.56728999e-10, "yes": 1, "no": 2, "missing": 2 , "children": [
    { "nodeid": 1, "depth": 1, "split": "f8", "split_condition": -1.05530953, "yes": 3, "no": 4, "missing": 4 , "children": [
      { "nodeid": 3, "leaf": -0.01477776 }, 
      { "nodeid": 4, "leaf": -0.0557832085 }
    ]}, 
    { "nodeid": 2, "depth": 1, "split": "f0", "split_condition": 0.339592844, "yes": 5, "no": 6, "missing": 6 , "children": [
      { "nodeid": 5, "depth": 2, "split": "f1", "split_condition": 0.268457919, "yes": 7, "no": 8, "missing": 8 , "children": [
        { "nodeid": 7, "leaf": 0.0237606149 }, 
        { "nodeid": 8, "leaf": -0.0560454428 }
      ]}, 
      { "nodeid": 6, "depth": 2, "split": "f2", "split_condition": 0.32322067, "yes": 9, "no": 10, "missing": 10 , "children": [
        { "nodeid": 9, "leaf": 0.0499873124 }, 
        { "nodeid": 10, "leaf": -0.014032118 }
      ]}
    ]}
  ]},
  { "nodeid": 0, "depth": 0, "split": "f5", "split_condition": 2.56728999e-10, "yes": 1, "no": 2, "missing": 2 , "children": [
    { "nodeid": 1, "depth": 1, "split": "f8", "split_condition": -1.05530953, "yes": 3, "no": 4, "missing": 4 , "children": [
      { "nodeid": 3, "leaf": -0.0143873021 }, 
      { "nodeid": 4, "leaf": -0.0551209114 }
    ]}, 
    { "nodeid": 2, "depth": 1, "split": "f0", "split_condition": 0.339592844, "yes": 5, "no": 6, "missing": 6 , "children": [
      { "nodeid": 5, "depth": 2, "split": "f1", "split_condition": 0.268457919, "yes": 7, "no": 8, "missing": 8 , "children": [
        { "nodeid": 7, "leaf": 0.0231846478 }, 
        { "nodeid": 8, "leaf": -0.0546205752 }
      ]}, 
      { "nodeid": 6, "depth": 2, "split": "f2", "split_condition": 0.32322067, "yes": 9, "no": 10, "missing": 10 , "children": [
        { "nodeid": 9, "leaf": 0.0497426651 }, 
        { "nodeid": 10, "leaf": -0.0136689143 }
      ]}
    ]}
  ]},
  { "nodeid": 0, "depth": 0, "split": "f5", "split_condition": 2.56728999e-10, "yes": 1, "no": 2, "missing": 2 , "children": [
    { "nodeid": 1, "depth": 1, "split": "f8", "split_condition": -1.05530953, "yes": 3, "no": 4, "missing": 4 , "children": [
      { "nodeid": 3, "leaf": -0.0140076531 }, 
      { "nodeid": 4, "leaf": -0.0544872545 }
    ]}, 
    { "nodeid": 2, "depth": 1, "split": "f0", "split_condition": 0.339592844, "yes": 5, "no": 6, "missing": 6 , "children": [
      { "nodeid": 5, "depth": 2, "split": "f1", "split_condition": 0.268457919, "yes": 7, "no": 8, "missing": 8 , "children": [
        { "nodeid": 7, "leaf": 0.0226241965 }, 
        { "nodeid": 8, "leaf": -0.0532707088 }
      ]}, 
      { "nodeid": 6, "depth": 2, "split": "f6", "split_condition": 0.68334496, "yes": 9, "no": 10, "missing": 10 , "children": [
        { "nodeid": 9, "leaf": -0.0138538824 }, 
        { "nodeid": 10, "leaf": 0.0495261215 }
      ]}
    ]}
  ]},
  { "nodeid": 0, "depth": 0, "split": "f5", "split_condition": 2.56728999e-10, "yes": 1, "no": 2, "missing": 2 , "children": [
    { "nodeid": 1, "depth": 1, "split": "f4", "split_condition": 0.570029318, "yes": 3, "no": 4, "missing": 4 , "children": [
      { "nodeid": 3, "leaf": -0.0557450838 }, 
      { "nodeid": 4, "depth": 2, "split": "f2", "split_condition": 0.22626467, "yes": 7, "no": 8, "missing": 8 , "children": [
        { "nodeid": 7, "leaf": -0.000287596107 }, 
        { "nodeid": 8, "leaf": -0.0315208174 }
      ]}
    ]}, 
    { "nodeid": 2, "depth": 1, "split": "f0", "split_condition": 0.339592844, "yes": 5, "no": 6, "missing": 6 , "children": [
      { "nodeid": 5, "depth": 2, "split": "f1", "split_condition": 0.268457919, "yes": 9, "no": 10, "missing": 10 , "children": [
        { "nodeid": 9, "leaf": 0.0220786873 }, 
        { "nodeid": 10, "leaf": -0.0519894771 }
      ]}, 
      { "nodeid": 6, "depth": 2, "split": "f3", "split_condition": 0.34342438, "yes": 11, "no": 12, "missing": 12 , "children": [
        { "nodeid": 11, "leaf": 0.0492675118 }, 
        { "nodeid": 12, "leaf": -0.0137002338 }
      ]}
    ]}
  ]},
  { "nodeid": 0, "depth": 0, "split": "f5", "split_condition": 2.56728999e-10, "yes": 1, "no": 2, "missing": 2 , "children": [
    { "nodeid": 1, "depth": 1, "split": "f8", "split_condition": -1.05530953, "yes": 3, "no": 4, "missing": 4 , "children": [
      { "nodeid": 3, "leaf": -0.0128213689 }, 
      { "nodeid": 4, "leaf": -0.0533313863 }
    ]}, 
    { "nodeid": 2, "depth": 1, "split": "f0", "split_condition": 0.339592844, "yes": 5, "no": 6, "missing": 6 , "children": [
      { "nodeid": 5, "depth": 2, "split": "f1", "split_condition": 0.268457919, "yes": 7, "no": 8, "missing": 8 , "children": [
        { "nodeid": 7, "leaf": 0.0215476025 }, 
        { "nodeid": 8, "leaf": -0.0507711954 }
      ]}, 
      { "nodeid": 6, "depth": 2, "split": "f3", "split_condition": 0.34342438, "yes": 9, "no": 10, "missing": 10 , "children": [
        { "nodeid": 9, "leaf": 0.0490283594 }, 
        { "nodeid": 10, "leaf": -0.0133499419 }
      ]}
    ]}
  ]},
  { "nodeid": 0, "depth": 0, "split": "f5", "split_condition": 2.56728999e-10, "yes": 1, "no": 2, "missing": 2 , "children": [
    { "nodeid": 1, "depth": 1, "split": "f4", "split_condition": 0.570029318, "yes": 3, "no": 4, "missing": 4 , "children": [
      { "nodeid": 3, "leaf": -0.0546055511 }, 
      { "nodeid": 4, "depth": 2, "split": "f6", "split_condition": -0.00794319529, "yes": 7, "no": 8, "missing": 8 , "children": [
        { "nodeid": 7, "leaf": -0.0305073448 }, 
        { "nodeid": 8, "leaf": 0.00107228698 }
      ]}
    ]}, 
    { "nodeid": 2, "depth": 1, "split": "f3", "split_condition": 0.371746629, "yes": 5, "no": 6, "missing": 6 , "children": [
      { "nodeid": 5, "depth": 2, "split": "f4", "split_condition": 0.573569179, "yes": 9, "no": 10, "missing": 10 , "children": [
        { "nodeid": 9, "depth": 3, "split": "f8", "split_condition": 0.438520759, "yes": 11, "no": 12, "missing": 12 , "children": [
          { "nodeid": 11, "leaf": -0.0298235156 }, 
          { "nodeid": 12, "leaf": 0.0150658851 }
        ]}, 
        { "nodeid": 10, "leaf": 0.0491036586 }
      ]}, 
      { "nodeid": 6, "leaf": -0.039113488 }
    ]}
  ]},
  { "nodeid": 0, "depth": 0, "split": "f5", "split_condition": 2.56728999e-10, "yes": 1, "no": 2, "missing": 2 , "children": [
    { "nodeid": 1, "depth": 1, "split": "f8", "split_condition": -1.05530953, "yes": 3, "no": 4, "missing": 4 , "children": [
      { "nodeid": 3, "leaf": -0.0117092608 }, 
      { "nodeid": 4, "leaf": -0.0522591844 }
    ]}, 
    { "nodeid": 2, "depth": 1, "split": "f0", "split_condition": 0.339592844, "yes": 5, "no": 6, "missing": 6 , "children": [
      { "nodeid": 5, "depth": 2, "split": "f1", "split_condition": 0.268457919, "yes": 7, "no": 8, "missing": 8 , "children": [
        { "nodeid": 7, "leaf": 0.0206646062 }, 
        { "nodeid": 8, "leaf": -0.0491047651 }
      ]}, 
      { "nodeid": 6, "depth": 2, "split": "f6", "split_condition": 0.708961725, "yes": 9, "no": 10, "missing": 10 , "children": [
        { "nodeid": 9, "leaf": -0.0118030189 }, 
        { "nodeid": 10, "leaf": 0.0485850461 }
      ]}
    ]}
  ]},
  { "nodeid": 0, "depth": 0, "split": "f4", "split_condition": 0.573569179, "yes": 1, "no": 2, "missing": 2 , "children": [
    { "nodeid": 1, "depth": 1, "split": "f8", "split_condition": 0.606362641, "yes": 3, "no": 4, "missing": 4 , "children": [
      { "nodeid": 3, "leaf": -0.0544870906 }, 
      { "nodeid": 4, "leaf": 0.00823039468 }
    ]}, 
    { "nodeid": 2, "depth": 1, "split": "f6", "split_condition": 0.64340663, "yes": 5, "no": 6, "missing": 6 , "children": [
      { "nodeid": 5, "depth": 2, "split": "f1", "split_condition": 0.415467352, "yes": 7, "no": 8, "missing": 8 , "children": [
        { "nodeid": 7, "leaf": -0.000815597072 }, 
        { "nodeid": 8, "leaf": -0.0377571359 }
      ]}, 
      { "nodeid": 6, "depth": 2, "split": "f1", "split_condition": 0.654856384, "yes": 9, "no": 10, "missing": 10 , "children": [
        { "nodeid": 9, "leaf": 0.0490177087 }, 
        { "nodeid": 10, "leaf": 0.00826423243 }
      ]}
    ]}
  ]},
  { "nodeid": 0, "depth": 0, "split": "f5", "split_condition": 2.56728999e-10, "yes": 1, "no": 2, "missing": 2 , "children": [
    { "nodeid": 1, "depth": 1, "split": "f8", "split_condition": -1.05530953, "yes": 3, "no": 4, "missing": 4 , "children": [
      { "nodeid": 3, "leaf": -0.0111944862 }, 
      { "nodeid": 4, "leaf": -0.0513013974 }
    ]}, 
    { "nodeid": 2, "depth": 1, "split": "f3", "split_condition": 0.371746629, "yes": 5, "no": 6, "missing": 6 , "children": [
      { "nodeid": 5, "depth": 2, "split": "f4", "split_condition": 0.573569179, "yes": 7, "no": 8, "missing": 8 , "children": [
        { "nodeid": 7, "depth": 3, "split": "f8", "split_condition": 0.438520759, "yes": 9, "no": 10, "missing": 10 , "children": [
          { "nodeid": 9, "leaf": -0.0272888038 }, 
          { "nodeid": 10, "leaf": 0.0148720415 }
        ]}, 
        { "nodeid": 8, "leaf": 0.0484311692 }
      ]}, 
      { "nodeid": 6, "leaf": -0.0372193158 }
    ]}
  ]},
  { "nodeid": 0, "depth": 0, "split": "f4", "split_condition": 0.573569179, "yes": 1, "no": 2, "missing": 2 , "children": [
    { "nodeid": 1, "depth": 1, "split": "f8", "split_condition": 0.606362641, "yes": 3, "no": 4, "missing": 4 , "children": [
      { "nodeid": 3, "depth": 2, "split": "f1", "split_condition": 0.673778355, "yes": 7, "no": 8, "missing": 8 , "children": [
        { "nodeid": 7, "leaf": -0.0565365665 }, 
        { "nodeid": 8, "leaf": -0.0184217654 }
      ]}, 
      { "nodeid": 4, "leaf": 0.00844858959 }
    ]}, 
    { "nodeid": 2, "depth": 1, "split": "f6", "split_condition": 0.64340663, "yes": 5, "no": 6, "missing": 6 , "children": [
      { "nodeid": 5, "depth": 2, "split": "f3", "split_condition": 0.34342438, "yes": 9, "no": 10, "missing": 10 , "children": [
        { "nodeid": 9, "leaf": -0.00330529176 }, 
        { "nodeid": 10, "leaf": -0.0356603824 }
      ]}, 
      { "nodeid": 6, "depth": 2, "split": "f1", "split_condition": 0.628941238, "yes": 11, "no": 12, "missing": 12 , "children": [
        { "nodeid": 11, "leaf": 0.0485503934 }, 
        { "nodeid": 12, "leaf": 0.00917491317 }
      ]}
    ]}
  ]},
  { "nodeid": 0, "depth": 0, "split": "f5", "split_condition": 2.56728999e-10, "yes": 1, "no": 2, "missing": 2 , "children": [
    { "nodeid": 1, "depth": 1, "split": "f5", "split_condition": 2.35363506e-10, "yes": 3, "no": 4, "missing": 4 , "children": [
      { "nodeid": 3, "leaf": -0.0505561121 }, 
      { "nodeid": 4, "leaf": -0.0112478388 }
    ]}, 
    { "nodeid": 2, "depth": 1, "split": "f0", "split_condition": 0.339592844, "yes": 5, "no": 6, "missing": 6 , "children": [
      { "nodeid": 5, "depth": 2, "split": "f1", "split_condition": 0.268457919, "yes": 7, "no": 8, "missing": 8 , "children": [
        { "nodeid": 7, "leaf": 0.0201447848 }, 
        { "nodeid": 8, "leaf": -0.0458187275 }
      ]}, 
      { "nodeid": 6, "depth": 2, "split": "f6", "split_condition": 0.709617138, "yes": 9, "no": 10, "missing": 10 , "children": [
        { "nodeid": 9, "leaf": -0.00911840703 }, 
        { "nodeid": 10, "leaf": 0.0476772301 }
      ]}
    ]}
  ]},
  { "nodeid": 0, "depth": 0, "split": "f4", "split_condition": 0.573569179, "yes": 1, "no": 2, "missing": 2 , "children": [
    { "nodeid": 1, "depth": 1, "split": "f8", "split_condition": 0.606362641, "yes": 3, "no": 4, "missing": 4 , "children": [
      { "nodeid": 3, "depth": 2, "split": "f1", "split_condition": 0.673778355, "yes": 7, "no": 8, "missing": 8 , "children": [
        { "nodeid": 7, "leaf": -0.0555374697 }, 
        { "nodeid": 8, "leaf": -0.0177192222 }
      ]}, 
      { "nodeid": 4, "leaf": 0.00856400002 }
    ]}, 
    { "nodeid": 2, "depth": 1, "split": "f6", "split_condition": 0.64340663, "yes": 5, "no": 6, "missing": 6 , "children": [
      { "nodeid": 5, "depth": 2, "split": "f1", "split_condition": 0.423698455, "yes": 9, "no": 10, "missing": 10 , "children": [
        { "nodeid": 9, "leaf": -0.00265466468 }, 
        { "nodeid": 10, "leaf": -0.0345027559 }
      ]}, 
      { "nodeid": 6, "depth": 2, "split": "f3", "split_condition": 0.292546779, "yes": 11, "no": 12, "missing": 12 , "children": [
        { "nodeid": 11, "leaf": 0.0480748005 }, 
        { "nodeid": 12, "leaf": 0.0092870146 }
      ]}
    ]}
  ]},
  { "nodeid": 0, "depth": 0, "split": "f5", "split_condition": 2.56728999e-10, "yes": 1, "no": 2, "missing": 2 , "children": [
    { "nodeid": 1, "depth": 1, "split": "f8", "split_condition": -1.05530953, "yes": 3, "no": 4, "missing": 4 , "children": [
      { "nodeid": 3, "leaf": -0.00984649267 }, 
      { "nodeid": 4, "leaf": -0.0496039651 }
    ]}, 
    { "nodeid": 2, "depth": 1, "split": "f3", "split_condition": 0.371746629, "yes": 5, "no": 6, "missing": 6 , "children": [
      { "nodeid": 5, "depth": 2, "split": "f0", "split_condition": 0.311315954, "yes": 7, "no": 8, "missing": 8 , "children": [
        { "nodeid": 7, "depth": 3, "split": "f8", "split_condition": 0.438520759, "yes": 9, "no": 10, "missing": 10 , "children": [
          { "nodeid": 9, "leaf": -0.0267266072 }, 
          { "nodeid": 10, "leaf": 0.0149116963 }
        ]}, 
        { "nodeid": 8, "leaf": 0.0474079512 }
      ]}, 
      { "nodeid": 6, "leaf": -0.0349273607 }
    ]}
  ]},
  { "nodeid": 0, "depth": 0, "split": "f5", "split_condition": 5.48660728e-10, "yes": 1, "no": 2, "missing": 2 , "children": [
    { "nodeid": 1, "depth": 1, "split": "f4", "split_condition": 0.573569179, "yes": 3, "no": 4, "missing": 4 , "children": [
      { "nodeid": 3, "depth": 2, "split": "f7", "split_condition": 1.72623193, "yes": 7, "no": 8, "missing": 8 , "children": [
        { "nodeid": 7, "leaf": -0.0541505106 }, 
        { "nodeid": 8, "leaf": -0.00957767852 }
      ]}, 
      { "nodeid": 4, "depth": 2, "split": "f2", "split_condition": 0.158090413, "yes": 9, "no": 10, "missing": 10 , "children": [
        { "nodeid": 9, "leaf": 0.0344021656 }, 
        { "nodeid": 10, "leaf": -0.0326058082 }
      ]}
    ]}, 
    { "nodeid": 2, "depth": 1, "split": "f3", "split_condition": 0.292546779, "yes": 5, "no": 6, "missing": 6 , "children": [
      { "nodeid": 5, "leaf": 0.0470830761 }, 
      { "nodeid": 6, "leaf": 0.00143229705 }
    ]}
  ]},
  { "nodeid": 0, "depth": 0, "split": "f5", "split_condition": 5.48660728e-10, "yes": 1, "no": 2, "missing": 2 , "children": [
    { "nodeid": 1, "depth": 1, "split": "f4", "split_condition": 0.573569179, "yes": 3, "no": 4, "missing": 4 , "children": [
      { "nodeid": 3, "depth": 2, "split": "f7", "split_condition": 1.72623193, "yes": 7, "no": 8, "missing": 8 , "children": [
        { "nodeid": 7, "leaf": -0.0535358079 }, 
        { "nodeid": 8, "leaf": -0.00934460573 }
      ]}, 
      { "nodeid": 4, "depth": 2, "split": "f6", "split_condition": 0.165681869, "yes": 9, "no": 10, "missing": 10 , "children": [
        { "nodeid": 9, "leaf": -0.0320623703 }, 
        { "nodeid": 10, "leaf": 0.0339116715 }
      ]}
    ]}, 
    { "nodeid": 2, "depth": 1, "split": "f3", "split_condition": 0.292546779, "yes": 5, "no": 6, "missing": 6 , "children": [
      { "nodeid": 5, "leaf": 0.0467908941 }, 
      { "nodeid": 6, "leaf": 0.00138763071 }
    ]}
  ]},
  { "nodeid": 0, "depth": 0, "split": "f5", "split_condition": 2.56728999e-10, "yes": 1, "no": 2, "missing": 2 , "children": [
    { "nodeid": 1, "depth": 1, "split": "f5", "split_condition": 2.35363506e-10, "yes": 3, "no": 4, "missing": 4 , "children": [
      { "nodeid": 3, "leaf": -0.0484069288 }, 
      { "nodeid": 4, "leaf": -0.00967217423 }
    ]}, 
    { "nodeid": 2, "depth": 1, "split": "f3", "split_condition": 0.371746629, "yes": 5, "no": 6, "missing": 6 , "children": [
      { "nodeid": 5, "depth": 2, "split": "f4", "split_condition": 0.573569179, "yes": 7, "no": 8, "missing": 8 , "children": [
        { "nodeid": 7, "depth": 3, "split": "f8", "split_condition": 0.424760133, "yes": 9, "no": 10, "missing": 10 , "children": [
          { "nodeid": 9, "leaf": -0.0219764169 }, 
          { "nodeid": 10, "leaf": 0.00951144192 }
        ]}, 
        { "nodeid": 8, "leaf": 0.0469519868 }
      ]}, 
      { "nodeid": 6, "leaf": -0.0334945507 }
    ]}
  ]},
  { "nodeid": 0, "depth": 0, "split": "f5", "split_condition": 5.48660728e-10, "yes": 1, "no": 2, "missing": 2 , "children": [
    { "nodeid": 1, "depth": 1, "split": "f4", "split_condition": 0.573569179, "yes": 3, "no": 4, "missing": 4 , "children": [
      { "nodeid": 3, "depth": 2, "split": "f7", "split_condition": 1.72623193, "yes": 7, "no": 8, "missing": 8 , "children": [
        { "nodeid": 7, "leaf": -0.0526367389 }, 
        { "nodeid": 8, "leaf": -0.00857741013 }
      ]}, 
      { "nodeid": 4, "depth": 2, "split": "f2", "split_condition": 0.158090413, "yes": 9, "no": 10, "missing": 10 , "children": [
        { "nodeid": 9, "leaf": 0.0331822932 }, 
        { "nodeid": 10, "leaf": -0.0309720021 }
      ]}
    ]}, 
    { "nodeid": 2, "depth": 1, "split": "f3", "split_condition": 0.292546779, "yes": 5, "no": 6, "missing": 6 , "children": [
      { "nodeid": 5, "leaf": 0.0462696292 }, 
      { "nodeid": 6, "leaf": 0.000797999965 }
    ]}
  ]},
  { "nodeid": 0, "depth": 0, "split": "f4", "split_condition": 0.573569179, "yes": 1, "no": 2, "missing": 2 , "children": [
    { "nodeid": 1, "depth": 1, "split": "f8", "split_condition": 0.606362641, "yes": 3, "no": 4, "missing": 4 , "children": [
      { "nodeid": 3, "depth": 2, "split": "f1", "split_condition": 0.673778355, "yes": 7, "no": 8, "missing": 8 , "children": [
        { "nodeid": 7, "leaf": -0.0528979711 }, 
        { "nodeid": 8, "leaf": -0.0151994331 }
      ]}, 
      { "nodeid": 4, "leaf": 0.0102211311 }
    ]}, 
    { "nodeid": 2, "depth": 1, "split": "f3", "split_condition": 0.371746629, "yes": 5, "no": 6, "missing": 6 , "children": [
      { "nodeid": 5, "depth": 2, "split": "f5", "split_condition": 2.39746223e-10, "yes": 9, "no": 10, "missing": 10 , "children": [
        { "nodeid": 9, "leaf": -0.00339613087 }, 
        { "nodeid": 10, "leaf": 0.0464965887 }
      ]}, 
      { "nodeid": 6, "leaf": -0.0337962322 }
    ]}
  ]},
  { "nodeid": 0, "depth": 0, "split": "f5", "split_condition": 5.48660728e-10, "yes": 1, "no": 2, "missing": 2 , "children": [
    { "nodeid": 1, "depth": 1, "split": "f4", "split_condition": 0.573569179, "yes": 3, "no": 4, "missing": 4 , "children": [
      { "nodeid": 3, "depth": 2, "split": "f7", "split_condition": 1.72623193, "yes": 7, "no": 8, "missing": 8 , "children": [
        { "nodeid": 7, "leaf": -0.0515767522 }, 
        { "nodeid": 8, "leaf": -0.00767560769 }
      ]}, 
      { "nodeid": 4, "depth": 2, "split": "f6", "split_condition": 0.165681869, "yes": 9, "no": 10, "missing": 10 , "children": [
        { "nodeid": 9, "leaf": -0.0302468725 }, 
        { "nodeid": 10, "leaf": 0.0323209576 }
      ]}
    ]}, 
    { "nodeid": 2, "depth": 1, "split": "f3", "split_condition": 0.292546779, "yes": 5, "no": 6, "missing": 6 , "children": [
      { "nodeid": 5, "leaf": 0.0457323752 }, 
      { "nodeid": 6, "leaf": 0.000397732627 }
    ]}
  ]},
  { "nodeid": 0, "depth": 0, "split": "f5", "split_condition": 2.56728999e-10, "yes": 1, "no": 2, "missing": 2 , "children": [
    { "nodeid": 1, "depth": 1, "split": "f5", "split_condition": 2.35363506e-10, "yes": 3, "no": 4, "missing": 4 , "children": [
      { "nodeid": 3, "leaf": -0.0468278825 }, 
      { "nodeid": 4, "leaf": -0.00824958738 }
    ]}, 
    { "nodeid": 2, "depth": 1, "split": "f0", "split_condition": 0.339592844, "yes": 5, "no": 6, "missing": 6 , "children": [
      { "nodeid": 5, "depth": 2, "split": "f1", "split_condition": 0.268457919, "yes": 7, "no": 8, "missing": 8 , "children": [
        { "nodeid": 7, "leaf": 0.0184521079 }, 
        { "nodeid": 8, "leaf": -0.0394338779 }
      ]}, 
      { "nodeid": 6, "depth": 2, "split": "f2", "split_condition": 0.311675251, "yes": 9, "no": 10, "missing": 10 , "children": [
        { "nodeid": 9, "leaf": 0.0454288088 }, 
        { "nodeid": 10, "leaf": -0.00293673296 }
      ]}
    ]}
  ]},
  { "nodeid": 0, "depth": 0, "split": "f4", "split_condition": 0.573569179, "yes": 1, "no": 2, "missing": 2 , "children": [
    { "nodeid": 1, "depth": 1, "split": "f8", "split_condition": 0.606362641, "yes": 3, "no": 4, "missing": 4 , "children": [
      { "nodeid": 3, "depth": 2, "split": "f1", "split_condition": 0.673778355, "yes": 7, "no": 8, "missing": 8 , "children": [
        { "nodeid": 7, "leaf": -0.0516058393 }, 
        { "nodeid": 8, "leaf": -0.0143428622 }
      ]}, 
      { "nodeid": 4, "leaf": 0.0105171641 }
    ]}, 
    { "nodeid": 2, "depth": 1, "split": "f3", "split_condition": 0.371746629, "yes": 5, "no": 6, "missing": 6 , "children": [
      { "nodeid": 5, "depth": 2, "split": "f5", "split_condition": 2.39746223e-10, "yes": 9, "no": 10, "missing": 10 , "children": [
        { "nodeid": 9, "leaf": -0.00253402046 }, 
        { "nodeid": 10, "leaf": 0.0458025709 }
      ]}, 
      { "nodeid": 6, "leaf": -0.0324841402 }
    ]}
  ]},
  { "nodeid": 0, "depth": 0, "split": "f5", "split_condition": 5.48660728e-10, "yes": 1, "no": 2, "missing": 2 , "children": [
    { "nodeid": 1, "depth": 1, "split": "f4", "split_condition": 0.573569179, "yes": 3, "no": 4, "missing": 4 , "children": [
      { "nodeid": 3, "depth": 2, "split": "f7", "split_condition": 1.69800997, "yes": 7, "no": 8, "missing": 8 , "children": [
        { "nodeid": 7, "leaf": -0.0501561463 }, 
        { "nodeid": 8, "leaf": -0.00770207588 }
      ]}, 
      { "nodeid": 4, "depth": 2, "split": "f2", "split_condition": 0.158090413, "yes": 9, "no": 10, "missing": 10 , "children": [
        { "nodeid": 9, "leaf": 0.0312450957 }, 
        { "nodeid": 10, "leaf": -0.0289384369 }
      ]}
    ]}, 
    { "nodeid": 2, "depth": 1, "split": "f3", "split_condition": 0.292546779, "yes": 5, "no": 6, "missing": 6 , "children": [
      { "nodeid": 5, "leaf": 0.0449052714 }, 
      { "nodeid": 6, "leaf": -0.00025198402 }
    ]}
  ]},
  { "nodeid": 0, "depth": 0, "split": "f5", "split_condition": 5.48660728e-10, "yes": 1, "no": 2, "missing": 2 , "children": [
    { "nodeid": 1, "depth": 1, "split": "f4", "split_condition": 0.573569179, "yes": 3, "no": 4, "missing": 4 , "children": [
      { "nodeid": 3, "depth": 2, "split": "f7", "split_condition": 1.69800997, "yes": 7, "no": 8, "missing": 8 , "children": [
        { "nodeid": 7, "leaf": -0.0496004708 }, 
        { "nodeid": 8, "leaf": -0.00751798553 }
      ]}, 
      { "nodeid": 4, "depth": 2, "split": "f6", "split_condition": 0.165681869, "yes": 9, "no": 10, "missing": 10 , "children": [
        { "nodeid": 9, "leaf": -0.0284684878 }, 
        { "nodeid": 10, "leaf": 0.0307858773 }
      ]}
    ]}, 
    { "nodeid": 2, "depth": 1, "split": "f3", "split_condition": 0.292546779, "yes": 5, "no": 6, "missing": 6 , "children": [
      { "nodeid": 5, "leaf": 0.044584047 }, 
      { "nodeid": 6, "leaf": -0.000244298222 }
    ]}
  ]},
  { "nodeid": 0, "depth": 0, "split": "f5", "split_condition": 2.56728999e-10, "yes": 1, "no": 2, "missing": 2 , "children": [
    { "nodeid": 1, "depth": 1, "split": "f5", "split_condition": 2.29302452e-10, "yes": 3, "no": 4, "missing": 4 , "children": [
      { "nodeid": 3, "leaf": -0.0452650301 }, 
      { "nodeid": 4, "leaf": -0.008256373 }
    ]}, 
    { "nodeid": 2, "depth": 1, "split": "f0", "split_condition": 0.339592844, "yes": 5, "no": 6, "missing": 6 , "children": [
      { "nodeid": 5, "depth": 2, "split": "f1", "split_condition": 0.268457919, "yes": 7, "no": 8, "missing": 8 , "children": [
        { "nodeid": 7, "leaf": 0.0174787696 }, 
        { "nodeid": 8, "leaf": -0.0366641544 }
      ]}, 
      { "nodeid": 6, "depth": 2, "split": "f6", "split_condition": 0.780806243, "yes": 9, "no": 10, "missing": 10 , "children": [
        { "nodeid": 9, "leaf": -0.00106817565 }, 
        { "nodeid": 10, "leaf": 0.0443694256 }
      ]}
    ]}
  ]},
  { "nodeid": 0, "depth": 0, "split": "f4", "split_condition": 0.573569179, "yes": 1, "no": 2, "missing": 2 , "children": [
    { "nodeid": 1, "depth": 1, "split": "f8", "split_condition": 0.606362641, "yes": 3, "no": 4, "missing": 4 , "children": [
      { "nodeid": 3, "leaf": -0.0465753935 }, 
      { "nodeid": 4, "leaf": 0.0110308276 }
    ]}, 
    { "nodeid": 2, "depth": 1, "split": "f3", "split_condition": 0.371746629, "yes": 5, "no": 6, "missing": 6 , "children": [
      { "nodeid": 5, "depth": 2, "split": "f5", "split_condition": 2.90522745e-10, "yes": 7, "no": 8, "missing": 8 , "children": [
        { "nodeid": 7, "leaf": 0.00134476309 }, 
        { "nodeid": 8, "leaf": 0.0447703414 }
      ]}, 
      { "nodeid": 6, "leaf": -0.0310141128 }
    ]}
  ]},
  { "nodeid": 0, "depth": 0, "split": "f5", "split_condition": 2.56728999e-10, "yes": 1, "no": 2, "missing": 2 , "children": [
    { "nodeid": 1, "depth": 1, "split": "f5", "split_condition": 2.29302452e-10, "yes": 3, "no": 4, "missing": 4 , "children": [
      { "nodeid": 3, "leaf": -0.0445366912 }, 
      { "nodeid": 4, "leaf": -0.00740824873 }
    ]}, 
    { "nodeid": 2, "depth": 1, "split": "f0", "split_condition": 0.339592844, "yes": 5, "no": 6, "missing": 6 , "children": [
      { "nodeid": 5, "depth": 2, "split": "f1", "split_condition": 0.268457919, "yes": 7, "no": 8, "missing": 8 , "children": [
        { "nodeid": 7, "leaf": 0.0169796217 }, 
        { "nodeid": 8, "leaf": -0.0353344791 }
      ]}, 
      { "nodeid": 6, "depth": 2, "split": "f3", "split_condition": 0.303495407, "yes": 9, "no": 10, "missing": 10 , "children": [
        { "nodeid": 9, "leaf": 0.0437550358 }, 
        { "nodeid": 10, "leaf": -0.000167979335 }
      ]}
    ]}
  ]},
  { "nodeid": 0, "depth": 0, "split": "f4", "split_condition": 0.543480992, "yes": 1, "no": 2, "missing": 2 , "children": [
    { "nodeid": 1, "depth": 1, "split": "f8", "split_condition": 0.406137645, "yes": 3, "no": 4, "missing": 4 , "children": [
      { "nodeid": 3, "leaf": -0.0481277555 }, 
      { "nodeid": 4, "leaf": -0.00868880749 }
    ]}, 
    { "nodeid": 2, "depth": 1, "split": "f6", "split_condition": 0.64340663, "yes": 5, "no": 6, "missing": 6 , "children": [
      { "nodeid": 5, "depth": 2, "split": "f5", "split_condition": 3.64853897e-10, "yes": 7, "no": 8, "missing": 8 , "children": [
        { "nodeid": 7, "leaf": -0.0298253633 }, 
        { "nodeid": 8, "leaf": 0.00594386272 }
      ]}, 
      { "nodeid": 6, "depth": 2, "split": "f6", "split_condition": 2.30058527, "yes": 9, "no": 10, "missing": 10 , "children": [
        { "nodeid": 9, "leaf": 0.0449128412 }, 
        { "nodeid": 10, "leaf": -0.00272672623 }
      ]}
    ]}
  ]},
  { "nodeid": 0, "depth": 0, "split": "f4", "split_condition": 0.543480992, "yes": 1, "no": 2, "missing": 2 , "children": [
    { "nodeid": 1, "depth": 1, "split": "f8", "split_condition": 0.406137645, "yes": 3, "no": 4, "missing": 4 , "children": [
      { "nodeid": 3, "leaf": -0.0475776158 }, 
      { "nodeid": 4, "leaf": -0.00848113745 }
    ]}, 
    { "nodeid": 2, "depth": 1, "split": "f6", "split_condition": 0.64340663, "yes": 5, "no": 6, "missing": 6 , "children": [
      { "nodeid": 5, "depth": 2, "split": "f5", "split_condition": 3.64853897e-10, "yes": 7, "no": 8, "missing": 8 , "children": [
        { "nodeid": 7, "leaf": -0.0293042157 }, 
        { "nodeid": 8, "leaf": 0.00579330372 }
      ]}, 
      { "nodeid": 6, "depth": 2, "split": "f6", "split_condition": 2.30058527, "yes": 9, "no": 10, "missing": 10 , "children": [
        { "nodeid": 9, "leaf": 0.0445900708 }, 
        { "nodeid": 10, "leaf": -0.00265467842 }
      ]}
    ]}
  ]},
  { "nodeid": 0, "depth": 0, "split": "f5", "split_condition": 2.56728999e-10, "yes": 1, "no": 2, "missing": 2 , "children": [
    { "nodeid": 1, "depth": 1, "split": "f4", "split_condition": 0.570029318, "yes": 3, "no": 4, "missing": 4 , "children": [
      { "nodeid": 3, "leaf": -0.044556804 }, 
      { "nodeid": 4, "leaf": -0.0101523707 }
    ]}, 
    { "nodeid": 2, "depth": 1, "split": "f3", "split_condition": 0.249919429, "yes": 5, "no": 6, "missing": 6 , "children": [
      { "nodeid": 5, "depth": 2, "split": "f0", "split_condition": 0.306376815, "yes": 7, "no": 8, "missing": 8 , "children": [
        { "nodeid": 7, "leaf": 0.00742473314 }, 
        { "nodeid": 8, "leaf": 0.0423882715 }
      ]}, 
      { "nodeid": 6, "depth": 2, "split": "f7", "split_condition": 1.40574431, "yes": 9, "no": 10, "missing": 10 , "children": [
        { "nodeid": 9, "leaf": -0.0369086973 }, 
        { "nodeid": 10, "leaf": 0.0284737851 }
      ]}
    ]}
  ]},
  { "nodeid": 0, "depth": 0, "split": "f5", "split_condition": 5.48660728e-10, "yes": 1, "no": 2, "missing": 2 , "children": [
    { "nodeid": 1, "depth": 1, "split": "f4", "split_condition": 0.573569179, "yes": 3, "no": 4, "missing": 4 , "children": [
      { "nodeid": 3, "depth": 2, "split": "f7", "split_condition": 1.63793087, "yes": 7, "no": 8, "missing": 8 , "children": [
        { "nodeid": 7, "leaf": -0.0465070568 }, 
        { "nodeid": 8, "leaf": -0.0084037967 }
      ]}, 
      { "nodeid": 4, "depth": 2, "split": "f2", "split_condition": 0.158090413, "yes": 9, "no": 10, "missing": 10 , "children": [
        { "nodeid": 9, "leaf": 0.0282351561 }, 
        { "nodeid": 10, "leaf": -0.0254692119 }
      ]}
    ]}, 
    { "nodeid": 2, "depth": 1, "split": "f3", "split_condition": 0.292546779, "yes": 5, "no": 6, "missing": 6 , "children": [
      { "nodeid": 5, "leaf": 0.0426231697 }, 
      { "nodeid": 6, "leaf": -0.00163872109 }
    ]}
  ]},
  { "nodeid": 0, "depth": 0, "split": "f5", "split_condition": 2.56728999e-10, "yes": 1, "no": 2, "missing": 2 , "children": [
    { "nodeid": 1, "depth": 1, "split": "f4", "split_condition": 0.570029318, "yes": 3, "no": 4, "missing": 4 , "children": [
      { "nodeid": 3, "leaf": -0.0436760634 }, 
      { "nodeid": 4, "leaf": -0.00980543345 }
    ]}, 
    { "nodeid": 2, "depth": 1, "split": "f4", "split_condition": 0.590335727, "yes": 5, "no": 6, "missing": 6 , "children": [
      { "nodeid": 5, "depth": 2, "split": "f3", "split_condition": 0.19666937, "yes": 7, "no": 8, "missing": 8 , "children": [
        { "nodeid": 7, "leaf": 0.0124181621 }, 
        { "nodeid": 8, "leaf": -0.0300083514 }
      ]}, 
      { "nodeid": 6, "depth": 2, "split": "f6", "split_condition": 0.709617138, "yes": 9, "no": 10, "missing": 10 , "children": [
        { "nodeid": 9, "leaf": 0.00277951243 }, 
        { "nodeid": 10, "leaf": 0.0421259217 }
      ]}
    ]}
  ]},
  { "nodeid": 0, "depth": 0, "split": "f5", "split_condition": 6.24752194e-10, "yes": 1, "no": 2, "missing": 2 , "children": [
    { "nodeid": 1, "depth": 1, "split": "f4", "split_condition": 0.573569179, "yes": 3, "no": 4, "missing": 4 , "children": [
      { "nodeid": 3, "depth": 2, "split": "f7", "split_condition": 1.63793087, "yes": 7, "no": 8, "missing": 8 , "children": [
        { "nodeid": 7, "leaf": -0.0456330255 }, 
        { "nodeid": 8, "leaf": -0.00766555173 }
      ]}, 
      { "nodeid": 4, "depth": 2, "split": "f2", "split_condition": 0.158090413, "yes": 9, "no": 10, "missing": 10 , "children": [
        { "nodeid": 9, "leaf": 0.0296090934 }, 
        { "nodeid": 10, "leaf": -0.0275482778 }
      ]}
    ]}, 
    { "nodeid": 2, "depth": 1, "split": "f6", "split_condition": 0.64340663, "yes": 5, "no": 6, "missing": 6 , "children": [
      { "nodeid": 5, "leaf": 0.00129680603 }, 
      { "nodeid": 6, "leaf": 0.0411001369 }
    ]}
  ]},
  { "nodeid": 0, "depth": 0, "split": "f5", "split_condition": 2.35363506e-10, "yes": 1, "no": 2, "missing": 2 , "children": [
    { "nodeid": 1, "leaf": -0.0421751738 }, 
    { "nodeid": 2, "depth": 1, "split": "f0", "split_condition": 0.339592844, "yes": 3, "no": 4, "missing": 4 , "children": [
      { "nodeid": 3, "depth": 2, "split": "f0", "split_condition": 0.260249168, "yes": 5, "no": 6, "missing": 6 , "children": [
        { "nodeid": 5, "leaf": 0.0126173869 }, 
        { "nodeid": 6, "leaf": -0.0357708819 }
      ]}, 
      { "nodeid": 4, "depth": 2, "split": "f3", "split_condition": 0.281141579, "yes": 7, "no": 8, "missing": 8 , "children": [
        { "nodeid": 7, "leaf": 0.0432276763 }, 
        { "nodeid": 8, "leaf": 0.00244894531 }
      ]}
    ]}
  ]},
  { "nodeid": 0, "depth": 0, "split": "f5", "split_condition": 2.56728999e-10, "yes": 1, "no": 2, "missing": 2 , "children": [
    { "nodeid": 1, "depth": 1, "split": "f4", "split_condition": 0.570029318, "yes": 3, "no": 4, "missing": 4 , "children": [
      { "nodeid": 3, "leaf": -0.0423879586 }, 
      { "nodeid": 4, "leaf": -0.00917377416 }
    ]}, 
    { "nodeid": 2, "depth": 1, "split": "f3", "split_condition": 0.249919429, "yes": 5, "no": 6, "missing": 6 , "children": [
      { "nodeid": 5, "depth": 2, "split": "f0", "split_condition": 0.306376815, "yes": 7, "no": 8, "missing": 8 , "children": [
        { "nodeid": 7, "leaf": 0.00783245731 }, 
        { "nodeid": 8, "leaf": 0.0407956652 }
      ]}, 
      { "nodeid": 6, "depth": 2, "split": "f7", "split_condition": 1.40574431, "yes": 9, "no": 10, "missing": 10 , "children": [
        { "nodeid": 9, "leaf": -0.0352239721 }, 
        { "nodeid": 10, "leaf": 0.0272623096 }
      ]}
    ]}
  ]},
  { "nodeid": 0, "depth": 0, "split": "f5", "split_condition": 2.35363506e-10, "yes": 1, "no": 2, "missing": 2 , "children": [
    { "nodeid": 1, "leaf": -0.0414213389 }, 
    { "nodeid": 2, "depth": 1, "split": "f0", "split_condition": 0.339592844, "yes": 3, "no": 4, "missing": 4 , "children": [
      { "nodeid": 3, "depth": 2, "split": "f0", "split_condition": 0.260249168, "yes": 5, "no": 6, "missing": 6 , "children": [
        { "nodeid": 5, "leaf": 0.0123766651 }, 
        { "nodeid": 6, "leaf": -0.0347128324 }
      ]}, 
      { "nodeid": 4, "depth": 2, "split": "f3", "split_condition": 0.273505807, "yes": 7, "no": 8, "missing": 8 , "children": [
        { "nodeid": 7, "leaf": 0.0426082984 }, 
        { "nodeid": 8, "leaf": 0.00302633271 }
      ]}
    ]}
  ]},
  { "nodeid": 0, "depth": 0, "split": "f5", "split_condition": 6.24752194e-10, "yes": 1, "no": 2, "missing": 2 , "children": [
    { "nodeid": 1, "depth": 1, "split": "f4", "split_condition": 0.573569179, "yes": 3, "no": 4, "missing": 4 , "children": [
      { "nodeid": 3, "depth": 2, "split": "f1", "split_condition": 0.105784714, "yes": 7, "no": 8, "missing": 8 , "children": [
        { "nodeid": 7, "leaf": -0.00811540708 }, 
        { "nodeid": 8, "leaf": -0.0438430794 }
      ]}, 
      { "nodeid": 4, "depth": 2, "split": "f2", "split_condition": 0.158090413, "yes": 9, "no": 10, "missing": 10 , "children": [
        { "nodeid": 9, "leaf": 0.0278067589 }, 
        { "nodeid": 10, "leaf": -0.0255211834 }
      ]}
    ]}, 
    { "nodeid": 2, "depth": 1, "split": "f3", "split_condition": 0.292546779, "yes": 5, "no": 6, "missing": 6 , "children": [
      { "nodeid": 5, "leaf": 0.040352121 }, 
      { "nodeid": 6, "leaf": 0.00175905123 }
    ]}
  ]},
  { "nodeid": 0, "depth": 0, "split": "f5", "split_condition": 2.35363506e-10, "yes": 1, "no": 2, "missing": 2 , "children": [
    { "nodeid": 1, "leaf": -0.0406847484 }, 
    { "nodeid": 2, "depth": 1, "split": "f0", "split_condition": 0.339592844, "yes": 3, "no": 4, "missing": 4 , "children": [
      { "nodeid": 3, "depth": 2, "split": "f0", "split_condition": 0.260249168, "yes": 5, "no": 6, "missing": 6 , "children": [
        { "nodeid": 5, "leaf": 0.0118691605 }, 
        { "nodeid": 6, "leaf": -0.0332777463 }
      ]}, 
      { "nodeid": 4, "depth": 2, "split": "f2", "split_condition": 0.265591532, "yes": 7, "no": 8, "missing": 8 , "children": [
        { "nodeid": 7, "leaf": 0.0419251397 }, 
        { "nodeid": 8, "leaf": 0.00342459581 }
      ]}
    ]}
  ]},
  { "nodeid": 0, "depth": 0, "split": "f4", "split_condition": 0.543480992, "yes": 1, "no": 2, "missing": 2 , "children": [
    { "nodeid": 1, "depth": 1, "split": "f1", "split_condition": 0.105784714, "yes": 3, "no": 4, "missing": 4 , "children": [
      { "nodeid": 3, "leaf": -0.00753276143 }, 
      { "nodeid": 4, "leaf": -0.0434912704 }
    ]}, 
    { "nodeid": 2, "depth": 1, "split": "f6", "split_condition": 0.64340663, "yes": 5, "no": 6, "missing": 6 , "children": [
      { "nodeid": 5, "depth": 2, "split": "f1", "split_condition": 0.35562706, "yes": 7, "no": 8, "missing": 8 , "children": [
        { "nodeid": 7, "leaf": 0.00509137427 }, 
        { "nodeid": 8, "leaf": -0.0261397939 }
      ]}, 
      { "nodeid": 6, "depth": 2, "split": "f6", "split_condition": 2.29264069, "yes": 9, "no": 10, "missing": 10 , "children": [
        { "nodeid": 9, "leaf": 0.041447591 }, 
        { "nodeid": 10, "leaf": 0.00297574024 }
      ]}
    ]}
  ]},
  { "nodeid": 0, "depth": 0, "split": "f5", "split_condition": 2.35363506e-10, "yes": 1, "no": 2, "missing": 2 , "children": [
    { "nodeid": 1, "leaf": -0.0399700962 }, 
    { "nodeid": 2, "depth": 1, "split": "f0", "split_condition": 0.339592844, "yes": 3, "no": 4, "missing": 4 , "children": [
      { "nodeid": 3, "depth": 2, "split": "f0", "split_condition": 0.260249168, "yes": 5, "no": 6, "missing": 6 , "children": [
        { "nodeid": 5, "leaf": 0.0118285753 }, 
        { "nodeid": 6, "leaf": -0.0323093161 }
      ]}, 
      { "nodeid": 4, "depth": 2, "split": "f2", "split_condition": 0.262466222, "yes": 7, "no": 8, "missing": 8 , "children": [
        { "nodeid": 7, "leaf": 0.0411530733 }, 
        { "nodeid": 8, "leaf": 0.00420040078 }
      ]}
    ]}
  ]},
  { "nodeid": 0, "depth": 0, "split": "f4", "split_condition": 0.543480992, "yes": 1, "no": 2, "missing": 2 , "children": [
    { "nodeid": 1, "depth": 1, "split": "f7", "split_condition": 1.43017554, "yes": 3, "no": 4, "missing": 4 , "children": [
      { "nodeid": 3, "leaf": -0.0424829535 }, 
      { "nodeid": 4, "leaf": -0.00772055238 }
    ]}, 
    { "nodeid": 2, "depth": 1, "split": "f6", "split_condition": 0.64340663, "yes": 5, "no": 6, "missing": 6 , "children": [
      { "nodeid": 5, "depth": 2, "split": "f1", "split_condition": 0.35562706, "yes": 7, "no": 8, "missing": 8 , "children": [
        { "nodeid": 7, "leaf": 0.00525109284 }, 
        { "nodeid": 8, "leaf": -0.0253181215 }
      ]}, 
      { "nodeid": 6, "depth": 2, "split": "f6", "split_condition": 2.29264069, "yes": 9, "no": 10, "missing": 10 , "children": [
        { "nodeid": 9, "leaf": 0.0407367013 }, 
        { "nodeid": 10, "leaf": 0.00282755098 }
      ]}
    ]}
  ]},
  { "nodeid": 0, "depth": 0, "split": "f5", "split_condition": 6.24752194e-10, "yes": 1, "no": 2, "missing": 2 , "children": [
    { "nodeid": 1, "depth": 1, "split": "f4", "split_condition": 0.573569179, "yes": 3, "no": 4, "missing": 4 , "children": [
      { "nodeid": 3, "depth": 2, "split": "f0", "split_condition": 0.239595577, "yes": 7, "no": 8, "missing": 8 , "children": [
        { "nodeid": 7, "leaf": -0.00748185767 }, 
        { "nodeid": 8, "leaf": -0.0417749658 }
      ]}, 
      { "nodeid": 4, "depth": 2, "split": "f2", "split_condition": 0.158090413, "yes": 9, "no": 10, "missing": 10 , "children": [
        { "nodeid": 9, "leaf": 0.0251597203 }, 
        { "nodeid": 10, "leaf": -0.0232601222 }
      ]}
    ]}, 
    { "nodeid": 2, "depth": 1, "split": "f3", "split_condition": 0.292546779, "yes": 5, "no": 6, "missing": 6 , "children": [
      { "nodeid": 5, "leaf": 0.038757965 }, 
      { "nodeid": 6, "leaf": 0.00125884404 }
    ]}
  ]},
  { "nodeid": 0, "depth": 0, "split": "f5", "split_condition": 2.56728999e-10, "yes": 1, "no": 2, "missing": 2 , "children": [
    { "nodeid": 1, "depth": 1, "split": "f6", "split_condition": 0.64340663, "yes": 3, "no": 4, "missing": 4 , "children": [
      { "nodeid": 3, "leaf": -0.0394374616 }, 
      { "nodeid": 4, "leaf": -0.0073350505 }
    ]}, 
    { "nodeid": 2, "depth": 1, "split": "f3", "split_condition": 0.249919429, "yes": 5, "no": 6, "missing": 6 , "children": [
      { "nodeid": 5, "depth": 2, "split": "f6", "split_condition": 0.652435124, "yes": 7, "no": 8, "missing": 8 , "children": [
        { "nodeid": 7, "leaf": 0.00888482388 }, 
        { "nodeid": 8, "leaf": 0.0379908718 }
      ]}, 
      { "nodeid": 6, "depth": 2, "split": "f7", "split_condition": 0.669062555, "yes": 9, "no": 10, "missing": 10 , "children": [
        { "nodeid": 9, "leaf": -0.0304312538 }, 
        { "nodeid": 10, "leaf": 0.017945556 }
      ]}
    ]}
  ]},
  { "nodeid": 0, "depth": 0, "split": "f5", "split_condition": 2.35363506e-10, "yes": 1, "no": 2, "missing": 2 , "children": [
    { "nodeid": 1, "leaf": -0.0386242382 }, 
    { "nodeid": 2, "depth": 1, "split": "f0", "split_condition": 0.339592844, "yes": 3, "no": 4, "missing": 4 , "children": [
      { "nodeid": 3, "depth": 2, "split": "f0", "split_condition": 0.260249168, "yes": 5, "no": 6, "missing": 6 , "children": [
        { "nodeid": 5, "leaf": 0.0117736878 }, 
        { "nodeid": 6, "leaf": -0.0304421075 }
      ]}, 
      { "nodeid": 4, "depth": 2, "split": "f3", "split_condition": 0.25406146, "yes": 7, "no": 8, "missing": 8 , "children": [
        { "nodeid": 7, "leaf": 0.0397527963 }, 
        { "nodeid": 8, "leaf": 0.00494105089 }
      ]}
    ]}
  ]},
  { "nodeid": 0, "depth": 0, "split": "f5", "split_condition": 2.35363506e-10, "yes": 1, "no": 2, "missing": 2 , "children": [
    { "nodeid": 1, "leaf": -0.0382109992 }, 
    { "nodeid": 2, "depth": 1, "split": "f0", "split_condition": 0.339592844, "yes": 3, "no": 4, "missing": 4 , "children": [
      { "nodeid": 3, "depth": 2, "split": "f0", "split_condition": 0.260249168, "yes": 5, "no": 6, "missing": 6 , "children": [
        { "nodeid": 5, "leaf": 0.0114802672 }, 
        { "nodeid": 6, "leaf": -0.0298512112 }
      ]}, 
      { "nodeid": 4, "depth": 2, "split": "f2", "split_condition": 0.255878478, "yes": 7, "no": 8, "missing": 8 , "children": [
        { "nodeid": 7, "leaf": 0.0393798463 }, 
        { "nodeid": 8, "leaf": 0.00473349495 }
      ]}
    ]}
  ]},
  { "nodeid": 0, "depth": 0, "split": "f4", "split_condition": 0.573569179, "yes": 1, "no": 2, "missing": 2 , "children": [
    { "nodeid": 1, "depth": 1, "split": "f8", "split_condition": 0.603465319, "yes": 3, "no": 4, "missing": 4 , "children": [
      { "nodeid": 3, "leaf": -0.039350953 }, 
      { "nodeid": 4, "leaf": 0.00741115538 }
    ]}, 
    { "nodeid": 2, "depth": 1, "split": "f3", "split_condition": 0.337569743, "yes": 5, "no": 6, "missing": 6 , "children": [
      { "nodeid": 5, "depth": 2, "split": "f5", "split_condition": 3.96250394e-10, "yes": 7, "no": 8, "missing": 8 , "children": [
        { "nodeid": 7, "leaf": 0.00964849815 }, 
        { "nodeid": 8, "leaf": 0.0381956585 }
      ]}, 
      { "nodeid": 6, "leaf": -0.0169641562 }
    ]}
  ]},
  { "nodeid": 0, "depth": 0, "split": "f5", "split_condition": 2.35363506e-10, "yes": 1, "no": 2, "missing": 2 , "children": [
    { "nodeid": 1, "leaf": -0.0375188328 }, 
    { "nodeid": 2, "depth": 1, "split": "f0", "split_condition": 0.339592844, "yes": 3, "no": 4, "missing": 4 , "children": [
      { "nodeid": 3, "depth": 2, "split": "f0", "split_condition": 0.260249168, "yes": 5, "no": 6, "missing": 6 , "children": [
        { "nodeid": 5, "leaf": 0.0112568429 }, 
        { "nodeid": 6, "leaf": -0.0288962126 }
      ]}, 
      { "nodeid": 4, "depth": 2, "split": "f2", "split_condition": 0.25499019, "yes": 7, "no": 8, "missing": 8 , "children": [
        { "nodeid": 7, "leaf": 0.0386858247 }, 
        { "nodeid": 8, "leaf": 0.0049752323 }
      ]}
    ]}
  ]},
  { "nodeid": 0, "depth": 0, "split": "f4", "split_condition": 0.543480992, "yes": 1, "no": 2, "missing": 2 , "children": [
    { "nodeid": 1, "depth": 1, "split": "f1", "split_condition": 0.12372566, "yes": 3, "no": 4, "missing": 4 , "children": [
      { "nodeid": 3, "leaf": -0.00767568126 }, 
      { "nodeid": 4, "leaf": -0.0396105461 }
    ]}, 
    { "nodeid": 2, "depth": 1, "split": "f6", "split_condition": 0.64340663, "yes": 5, "no": 6, "missing": 6 , "children": [
      { "nodeid": 5, "leaf": -0.0111945411 }, 
      { "nodeid": 6, "depth": 2, "split": "f6", "split_condition": 2.28407812, "yes": 7, "no": 8, "missing": 8 , "children": [
        { "nodeid": 7, "leaf": 0.0381068997 }, 
        { "nodeid": 8, "leaf": 0.00567547185 }
      ]}
    ]}
  ]},
  { "nodeid": 0, "depth": 0, "split": "f5", "split_condition": 2.56728999e-10, "yes": 1, "no": 2, "missing": 2 , "children": [
    { "nodeid": 1, "depth": 1, "split": "f6", "split_condition": 0.0791697502, "yes": 3, "no": 4, "missing": 4 , "children": [
      { "nodeid": 3, "leaf": -0.0365362354 }, 
      { "nodeid": 4, "leaf": -0.00927845854 }
    ]}, 
    { "nodeid": 2, "depth": 1, "split": "f3", "split_condition": 0.249919429, "yes": 5, "no": 6, "missing": 6 , "children": [
      { "nodeid": 5, "depth": 2, "split": "f3", "split_condition": 0.114561163, "yes": 7, "no": 8, "missing": 8 , "children": [
        { "nodeid": 7, "leaf": 0.00830383506 }, 
        { "nodeid": 8, "leaf": 0.0374720357 }
      ]}, 
      { "nodeid": 6, "leaf": -0.006866707 }
    ]}
  ]},
  { "nodeid": 0, "depth": 0, "split": "f4", "split_condition": 0.573569179, "yes": 1, "no": 2, "missing": 2 , "children": [
    { "nodeid": 1, "depth": 1, "split": "f8", "split_condition": 0.526711941, "yes": 3, "no": 4, "missing": 4 , "children": [
      { "nodeid": 3, "leaf": -0.0379316434 }, 
      { "nodeid": 4, "leaf": 0.00686564902 }
    ]}, 
    { "nodeid": 2, "depth": 1, "split": "f6", "split_condition": 0.64340663, "yes": 5, "no": 6, "missing": 6 , "children": [
      { "nodeid": 5, "leaf": -0.0120499609 }, 
      { "nodeid": 6, "leaf": 0.0348344892 }
    ]}
  ]},
  { "nodeid": 0, "depth": 0, "split": "f5", "split_condition": 6.24752194e-10, "yes": 1, "no": 2, "missing": 2 , "children": [
    { "nodeid": 1, "depth": 1, "split": "f5", "split_condition": 2.35363506e-10, "yes": 3, "no": 4, "missing": 4 , "children": [
      { "nodeid": 3, "leaf": -0.0362355337 }, 
      { "nodeid": 4, "depth": 2, "split": "f4", "split_condition": 0.573569179, "yes": 7, "no": 8, "missing": 8 , "children": [
        { "nodeid": 7, "leaf": -0.0184226483 }, 
        { "nodeid": 8, "leaf": 0.0152873341 }
      ]}
    ]}, 
    { "nodeid": 2, "depth": 1, "split": "f3", "split_condition": 0.292546779, "yes": 5, "no": 6, "missing": 6 , "children": [
      { "nodeid": 5, "leaf": 0.0359249637 }, 
      { "nodeid": 6, "leaf": 0.000666670443 }
    ]}
  ]},
  { "nodeid": 0, "depth": 0, "split": "f5", "split_condition": 2.35363506e-10, "yes": 1, "no": 2, "missing": 2 , "children": [
    { "nodeid": 1, "leaf": -0.0358252712 }, 
    { "nodeid": 2, "depth": 1, "split": "f0", "split_condition": 0.339592844, "yes": 3, "no": 4, "missing": 4 , "children": [
      { "nodeid": 3, "depth": 2, "split": "f0", "split_condition": 0.260249168, "yes": 5, "no": 6, "missing": 6 , "children": [
        { "nodeid": 5, "leaf": 0.0113166198 }, 
        { "nodeid": 6, "leaf": -0.0274176355 }
      ]}, 
      { "nodeid": 4, "depth": 2, "split": "f2", "split_condition": 0.251468539, "yes": 7, "no": 8, "missing": 8 , "children": [
        { "nodeid": 7, "leaf": 0.0369051807 }, 
        { "nodeid": 8, "leaf": 0.00589272706 }
      ]}
    ]}
  ]},
  { "nodeid": 0, "depth": 0, "split": "f5", "split_condition": 6.24752194e-10, "yes": 1, "no": 2, "missing": 2 , "children": [
    { "nodeid": 1, "depth": 1, "split": "f6", "split_condition": -0.186734989, "yes": 3, "no": 4, "missing": 4 , "children": [
      { "nodeid": 3, "leaf": -0.0367012955 }, 
      { "nodeid": 4, "depth": 2, "split": "f3", "split_condition": 0.158798516, "yes": 7, "no": 8, "missing": 8 , "children": [
        { "nodeid": 7, "leaf": 0.0265701357 }, 
        { "nodeid": 8, "leaf": -0.0274721123 }
      ]}
    ]}, 
    { "nodeid": 2, "depth": 1, "split": "f6", "split_condition": 0.64340663, "yes": 5, "no": 6, "missing": 6 , "children": [
      { "nodeid": 5, "leaf": -0.000286103896 }, 
      { "nodeid": 6, "leaf": 0.0347839519 }
    ]}
  ]},
  { "nodeid": 0, "depth": 0, "split": "f4", "split_condition": 0.543480992, "yes": 1, "no": 2, "missing": 2 , "children": [
    { "nodeid": 1, "depth": 1, "split": "f8", "split_condition": 0.194288597, "yes": 3, "no": 4, "missing": 4 , "children": [
      { "nodeid": 3, "leaf": -0.0362830497 }, 
      { "nodeid": 4, "leaf": -0.00979999825 }
    ]}, 
    { "nodeid": 2, "depth": 1, "split": "f5", "split_condition": 6.24752194e-10, "yes": 5, "no": 6, "missing": 6 , "children": [
      { "nodeid": 5, "depth": 2, "split": "f0", "split_condition": 0.339592844, "yes": 7, "no": 8, "missing": 8 , "children": [
        { "nodeid": 7, "leaf": -0.0239050649 }, 
        { "nodeid": 8, "leaf": 0.011862685 }
      ]}, 
      { "nodeid": 6, "leaf": 0.033063408 }
    ]}
  ]},
  { "nodeid": 0, "depth": 0, "split": "f5", "split_condition": 2.35363506e-10, "yes": 1, "no": 2, "missing": 2 , "children": [
    { "nodeid": 1, "leaf": -0.0348219052 }, 
    { "nodeid": 2, "depth": 1, "split": "f4", "split_condition": 0.573569179, "yes": 3, "no": 4, "missing": 4 , "children": [
      { "nodeid": 3, "leaf": -0.0120637072 }, 
      { "nodeid": 4, "depth": 2, "split": "f2", "split_condition": 0.304593354, "yes": 5, "no": 6, "missing": 6 , "children": [
        { "nodeid": 5, "leaf": 0.0369776674 }, 
        { "nodeid": 6, "leaf": 0.000287534407 }
      ]}
    ]}
  ]},
  { "nodeid": 0, "depth": 0, "split": "f5", "split_condition": 2.35363506e-10, "yes": 1, "no": 2, "missing": 2 , "children": [
    { "nodeid": 1, "leaf": -0.034416195 }, 
    { "nodeid": 2, "depth": 1, "split": "f4", "split_condition": 0.573569179, "yes": 3, "no": 4, "missing": 4 , "children": [
      { "nodeid": 3, "leaf": -0.011673837 }, 
      { "nodeid": 4, "depth": 2, "split": "f2", "split_condition": 0.304593354, "yes": 5, "no": 6, "missing": 6 , "children": [
        { "nodeid": 5, "leaf": 0.0365781449 }, 
        { "nodeid": 6, "leaf": 0.000280343433 }
      ]}
    ]}
  ]},
  { "nodeid": 0, "depth": 0, "split": "f5", "split_condition": 2.56728999e-10, "yes": 1, "no": 2, "missing": 2 , "children": [
    { "nodeid": 1, "leaf": -0.0295880344 }, 
    { "nodeid": 2, "depth": 1, "split": "f3", "split_condition": 0.249919429, "yes": 3, "no": 4, "missing": 4 , "children": [
      { "nodeid": 3, "depth": 2, "split": "f3", "split_condition": 0.120099492, "yes": 5, "no": 6, "missing": 6 , "children": [
        { "nodeid": 5, "leaf": 0.00789648853 }, 
        { "nodeid": 6, "leaf": 0.0349625126 }
      ]}, 
      { "nodeid": 4, "leaf": -0.00725323334 }
    ]}
  ]},
  { "nodeid": 0, "depth": 0, "split": "f4", "split_condition": 0.543480992, "yes": 1, "no": 2, "missing": 2 , "children": [
    { "nodeid": 1, "depth": 1, "split": "f8", "split_condition": 0.194288597, "yes": 3, "no": 4, "missing": 4 , "children": [
      { "nodeid": 3, "leaf": -0.0349108055 }, 
      { "nodeid": 4, "leaf": -0.00851857197 }
    ]}, 
    { "nodeid": 2, "depth": 1, "split": "f5", "split_condition": 6.24752194e-10, "yes": 5, "no": 6, "missing": 6 , "children": [
      { "nodeid": 5, "depth": 2, "split": "f0", "split_condition": 0.339592844, "yes": 7, "no": 8, "missing": 8 , "children": [
        { "nodeid": 7, "leaf": -0.0231375899 }, 
        { "nodeid": 8, "leaf": 0.011493451 }
      ]}, 
      { "nodeid": 6, "leaf": 0.0317672454 }
    ]}
  ]},
  { "nodeid": 0, "depth": 0, "split": "f5", "split_condition": 2.35363506e-10, "yes": 1, "no": 2, "missing": 2 , "children": [
    { "nodeid": 1, "leaf": -0.0334349833 }, 
    { "nodeid": 2, "depth": 1, "split": "f4", "split_condition": 0.573569179, "yes": 3, "no": 4, "missing": 4 , "children": [
      { "nodeid": 3, "leaf": -0.0113846734 }, 
      { "nodeid": 4, "depth": 2, "split": "f3", "split_condition": 0.303495407, "yes": 5, "no": 6, "missing": 6 , "children": [
        { "nodeid": 5, "leaf": 0.0356988758 }, 
        { "nodeid": 6, "leaf": 0.000767937396 }
      ]}
    ]}
  ]},
  { "nodeid": 0, "depth": 0, "split": "f4", "split_condition": 0.543480992, "yes": 1, "no": 2, "missing": 2 , "children": [
    { "nodeid": 1, "depth": 1, "split": "f8", "split_condition": 0.139330775, "yes": 3, "no": 4, "missing": 4 , "children": [
      { "nodeid": 3, "leaf": -0.0338909775 }, 
      { "nodeid": 4, "leaf": -0.0086083943 }
    ]}, 
    { "nodeid": 2, "depth": 1, "split": "f5", "split_condition": 6.24752194e-10, "yes": 5, "no": 6, "missing": 6 , "children": [
      { "nodeid": 5, "leaf": -0.00786503404 }, 
      { "nodeid": 6, "leaf": 0.0309699923 }
    ]}
  ]},
  { "nodeid": 0, "depth": 0, "split": "f5", "split_condition": 2.35363506e-10, "yes": 1, "no": 2, "missing": 2 , "children": [
    { "nodeid": 1, "leaf": -0.0328088924 }, 
    { "nodeid": 2, "depth": 1, "split": "f4", "split_condition": 0.573569179, "yes": 3, "no": 4, "missing": 4 , "children": [
      { "nodeid": 3, "leaf": -0.0108489562 }, 
      { "nodeid": 4, "depth": 2, "split": "f2", "split_condition": 0.296230823, "yes": 5, "no": 6, "missing": 6 , "children": [
        { "nodeid": 5, "leaf": 0.0351298228 }, 
        { "nodeid": 6, "leaf": 0.000228941368 }
      ]}
    ]}
  ]},
  { "nodeid": 0, "depth": 0, "split": "f5", "split_condition": 2.35363506e-10, "yes": 1, "no": 2, "missing": 2 , "children": [
    { "nodeid": 1, "leaf": -0.0324130952 }, 
    { "nodeid": 2, "depth": 1, "split": "f4", "split_condition": 0.573569179, "yes": 3, "no": 4, "missing": 4 , "children": [
      { "nodeid": 3, "leaf": -0.0105027258 }, 
      { "nodeid": 4, "depth": 2, "split": "f3", "split_condition": 0.303495407, "yes": 5, "no": 6, "missing": 6 , "children": [
        { "nodeid": 5, "leaf": 0.0347446017 }, 
        { "nodeid": 6, "leaf": 0.000153347646 }
      ]}
    ]}
  ]},
  { "nodeid": 0, "depth": 0, "split": "f5", "split_condition": 2.35363506e-10, "yes": 1, "no": 2, "missing": 2 , "children": [
    { "nodeid": 1, "leaf": -0.0320198201 }, 
    { "nodeid": 2, "depth": 1, "split": "f0", "split_condition": 0.339592844, "yes": 3, "no": 4, "missing": 4 , "children": [
      { "nodeid": 3, "depth": 2, "split": "f0", "split_condition": 0.260249168, "yes": 5, "no": 6, "missing": 6 , "children": [
        { "nodeid": 5, "leaf": 0.0116925268 }, 
        { "nodeid": 6, "leaf": -0.0249947589 }
      ]}, 
      { "nodeid": 4, "depth": 2, "split": "f3", "split_condition": 0.221946999, "yes": 7, "no": 8, "missing": 8 , "children": [
        { "nodeid": 7, "leaf": 0.0325424485 }, 
        { "nodeid": 8, "leaf": 0.00655643269 }
      ]}
    ]}
  ]},
  { "nodeid": 0, "depth": 0, "split": "f4", "split_condition": 0.543480992, "yes": 1, "no": 2, "missing": 2 , "children": [
    { "nodeid": 1, "depth": 1, "split": "f8", "split_condition": 0.0344822332, "yes": 3, "no": 4, "missing": 4 , "children": [
      { "nodeid": 3, "leaf": -0.032375332 }, 
      { "nodeid": 4, "leaf": -0.00807270408 }
    ]}, 
    { "nodeid": 2, "depth": 1, "split": "f5", "split_condition": 7.08012815e-10, "yes": 5, "no": 6, "missing": 6 , "children": [
      { "nodeid": 5, "depth": 2, "split": "f3", "split_condition": 0.183435336, "yes": 7, "no": 8, "missing": 8 , "children": [
        { "nodeid": 7, "leaf": 0.0143519389 }, 
        { "nodeid": 8, "leaf": -0.0238717701 }
      ]}, 
      { "nodeid": 6, "leaf": 0.0331012793 }
    ]}
  ]},
  { "nodeid": 0, "depth": 0, "split": "f5", "split_condition": 2.35363506e-10, "yes": 1, "no": 2, "missing": 2 , "children": [
    { "nodeid": 1, "leaf": -0.0313655846 }, 
    { "nodeid": 2, "depth": 1, "split": "f4", "split_condition": 0.573569179, "yes": 3, "no": 4, "missing": 4 , "children": [
      { "nodeid": 3, "leaf": -0.0100626685 }, 
      { "nodeid": 4, "depth": 2, "split": "f2", "split_condition": 0.281711072, "yes": 5, "no": 6, "missing": 6 , "children": [
        { "nodeid": 5, "leaf": 0.0336062573 }, 
        { "nodeid": 6, "leaf": 0.000795893196 }
      ]}
    ]}
  ]},
  { "nodeid": 0, "depth": 0, "split": "f5", "split_condition": 2.35363506e-10, "yes": 1, "no": 2, "missing": 2 , "children": [
    { "nodeid": 1, "leaf": -0.0309797358 }, 
    { "nodeid": 2, "depth": 1, "split": "f6", "split_condition": 0.64340663, "yes": 3, "no": 4, "missing": 4 , "children": [
      { "nodeid": 3, "depth": 2, "split": "f0", "split_condition": 0.260249168, "yes": 5, "no": 6, "missing": 6 , "children": [
        { "nodeid": 5, "leaf": 0.0116590671 }, 
        { "nodeid": 6, "leaf": -0.0234075207 }
      ]}, 
      { "nodeid": 4, "leaf": 0.0267239101 }
    ]}
  ]},
  { "nodeid": 0, "depth": 0, "split": "f4", "split_condition": 0.543480992, "yes": 1, "no": 2, "missing": 2 , "children": [
    { "nodeid": 1, "depth": 1, "split": "f8", "split_condition": 0.0299234558, "yes": 3, "no": 4, "missing": 4 , "children": [
      { "nodeid": 3, "leaf": -0.0312643461 }, 
      { "nodeid": 4, "leaf": -0.00783309434 }
    ]}, 
    { "nodeid": 2, "depth": 1, "split": "f5", "split_condition": 7.08012815e-10, "yes": 5, "no": 6, "missing": 6 , "children": [
      { "nodeid": 5, "depth": 2, "split": "f3", "split_condition": 0.183435336, "yes": 7, "no": 8, "missing": 8 , "children": [
        { "nodeid": 7, "leaf": 0.0136365956 }, 
        { "nodeid": 8, "leaf": -0.02303092 }
      ]}, 
      { "nodeid": 6, "leaf": 0.0322098471 }
    ]}
  ]},
  { "nodeid": 0, "depth": 0, "split": "f8", "split_condition": 0.68087095, "yes": 1, "no": 2, "missing": 2 , "children": [
    { "nodeid": 1, "depth": 1, "split": "f4", "split_condition": 0.573569179, "yes": 3, "no": 4, "missing": 4 , "children": [
      { "nodeid": 3, "leaf": -0.0348321125 }, 
      { "nodeid": 4, "depth": 2, "split": "f6", "split_condition": 0.676382422, "yes": 5, "no": 6, "missing": 6 , "children": [
        { "nodeid": 5, "leaf": -0.0099757947 }, 
        { "nodeid": 6, "leaf": 0.0220537968 }
      ]}
    ]}, 
    { "nodeid": 2, "leaf": 0.0273990631 }
  ]},
  { "nodeid": 0, "depth": 0, "split": "f6", "split_condition": -0.276442498, "yes": 1, "no": 2, "missing": 2 , "children": [
    { "nodeid": 1, "leaf": -0.0310796481 }, 
    { "nodeid": 2, "depth": 1, "split": "f3", "split_condition": 0.249919429, "yes": 3, "no": 4, "missing": 4 , "children": [
      { "nodeid": 3, "depth": 2, "split": "f5", "split_condition": 2.96606267e-10, "yes": 5, "no": 6, "missing": 6 , "children": [
        { "nodeid": 5, "leaf": 0.0057054339 }, 
        { "nodeid": 6, "leaf": 0.0320522226 }
      ]}, 
      { "nodeid": 4, "leaf": -0.0117060179 }
    ]}
  ]}
]